[
    {
        "PPG": "0.40078",
        "ABP": "66.297",
        "ECG": "0.21362"
    },
    {
        "PPG": "0.41838",
        "ABP": "66.102",
        "ECG": "0.20898"
    },
    {
        "PPG": "0.43695",
        "ABP": "65.906",
        "ECG": "0.39938"
    },
    {
        "PPG": "0.4565",
        "ABP": "65.711",
        "ECG": "0.5"
    },
    {
        "PPG": "0.47605",
        "ABP": "65.515",
        "ECG": "0.56037"
    },
    {
        "PPG": "0.4956",
        "ABP": "65.515",
        "ECG": "0.56966"
    },
    {
        "PPG": "0.51417",
        "ABP": "65.515",
        "ECG": "0.58514"
    },
    {
        "PPG": "0.53079",
        "ABP": "65.319",
        "ECG": "0.59598"
    },
    {
        "PPG": "0.54643",
        "ABP": "65.124",
        "ECG": "0.58514"
    },
    {
        "PPG": "0.55816",
        "ABP": "64.928",
        "ECG": "0.60526"
    },
    {
        "PPG": "0.56794",
        "ABP": "64.537",
        "ECG": "0.58978"
    },
    {
        "PPG": "0.57478",
        "ABP": "64.342",
        "ECG": "0.60991"
    },
    {
        "PPG": "0.57869",
        "ABP": "63.95",
        "ECG": "0.59598"
    },
    {
        "PPG": "0.58065",
        "ABP": "63.559",
        "ECG": "0.62074"
    },
    {
        "PPG": "0.57967",
        "ABP": "63.168",
        "ECG": "0.60991"
    },
    {
        "PPG": "0.57869",
        "ABP": "62.582",
        "ECG": "0.63003"
    },
    {
        "PPG": "0.57674",
        "ABP": "62.19",
        "ECG": "0.61455"
    },
    {
        "PPG": "0.57478",
        "ABP": "61.604",
        "ECG": "0.64087"
    },
    {
        "PPG": "0.57283",
        "ABP": "61.017",
        "ECG": "0.63467"
    },
    {
        "PPG": "0.56989",
        "ABP": "60.43",
        "ECG": "0.67028"
    },
    {
        "PPG": "0.56403",
        "ABP": "60.039",
        "ECG": "0.66563"
    },
    {
        "PPG": "0.55718",
        "ABP": "59.648",
        "ECG": "0.71517"
    },
    {
        "PPG": "0.55034",
        "ABP": "59.452",
        "ECG": "0.73065"
    },
    {
        "PPG": "0.54154",
        "ABP": "59.257",
        "ECG": "0.77554"
    },
    {
        "PPG": "0.5347",
        "ABP": "59.452",
        "ECG": "0.78638"
    },
    {
        "PPG": "0.52884",
        "ABP": "59.648",
        "ECG": "0.82043"
    },
    {
        "PPG": "0.52493",
        "ABP": "60.235",
        "ECG": "0.81579"
    },
    {
        "PPG": "0.52004",
        "ABP": "61.408",
        "ECG": "0.82043"
    },
    {
        "PPG": "0.51515",
        "ABP": "63.559",
        "ECG": "0.79102"
    },
    {
        "PPG": "0.50929",
        "ABP": "67.275",
        "ECG": "0.7709"
    },
    {
        "PPG": "0.50244",
        "ABP": "72.751",
        "ECG": "0.71981"
    },
    {
        "PPG": "0.4956",
        "ABP": "79.791",
        "ECG": "0.69505"
    },
    {
        "PPG": "0.48974",
        "ABP": "87.614",
        "ECG": "0.6548"
    },
    {
        "PPG": "0.48289",
        "ABP": "95.437",
        "ECG": "0.63467"
    },
    {
        "PPG": "0.47605",
        "ABP": "101.89",
        "ECG": "0.60991"
    },
    {
        "PPG": "0.46921",
        "ABP": "106.39",
        "ECG": "0.60062"
    },
    {
        "PPG": "0.46334",
        "ABP": "109.13",
        "ECG": "0.60526"
    },
    {
        "PPG": "0.4565",
        "ABP": "109.91",
        "ECG": "0.58514"
    },
    {
        "PPG": "0.45064",
        "ABP": "109.32",
        "ECG": "0.60062"
    },
    {
        "PPG": "0.44477",
        "ABP": "107.37",
        "ECG": "0.5805"
    },
    {
        "PPG": "0.43988",
        "ABP": "104.43",
        "ECG": "0.58978"
    },
    {
        "PPG": "0.43402",
        "ABP": "100.52",
        "ECG": "0.5805"
    },
    {
        "PPG": "0.42815",
        "ABP": "96.024",
        "ECG": "0.60991"
    },
    {
        "PPG": "0.42131",
        "ABP": "91.134",
        "ECG": "0.60526"
    },
    {
        "PPG": "0.41544",
        "ABP": "86.05",
        "ECG": "0.60991"
    },
    {
        "PPG": "0.40958",
        "ABP": "81.356",
        "ECG": "0.58514"
    },
    {
        "PPG": "0.40371",
        "ABP": "77.054",
        "ECG": "0.57585"
    },
    {
        "PPG": "0.39785",
        "ABP": "73.533",
        "ECG": "0.54489"
    },
    {
        "PPG": "0.39296",
        "ABP": "70.991",
        "ECG": "0.54954"
    },
    {
        "PPG": "0.3871",
        "ABP": "69.426",
        "ECG": "0.50929"
    },
    {
        "PPG": "0.38025",
        "ABP": "69.035",
        "ECG": "0.51548"
    },
    {
        "PPG": "0.37634",
        "ABP": "69.035",
        "ECG": "0.49536"
    },
    {
        "PPG": "0.37146",
        "ABP": "69.818",
        "ECG": "0.5"
    },
    {
        "PPG": "0.36559",
        "ABP": "70.6",
        "ECG": "0.47523"
    },
    {
        "PPG": "0.35973",
        "ABP": "71.578",
        "ECG": "0.49071"
    },
    {
        "PPG": "0.35288",
        "ABP": "72.36",
        "ECG": "0.47059"
    },
    {
        "PPG": "0.34702",
        "ABP": "73.142",
        "ECG": "0.4644"
    },
    {
        "PPG": "0.34213",
        "ABP": "73.533",
        "ECG": "0.47523"
    },
    {
        "PPG": "0.33724",
        "ABP": "73.533",
        "ECG": "0.45975"
    },
    {
        "PPG": "0.33431",
        "ABP": "73.338",
        "ECG": "0.47059"
    },
    {
        "PPG": "0.33236",
        "ABP": "72.947",
        "ECG": "0.45511"
    },
    {
        "PPG": "0.33236",
        "ABP": "72.36",
        "ECG": "0.47059"
    },
    {
        "PPG": "0.33431",
        "ABP": "71.578",
        "ECG": "0.45511"
    },
    {
        "PPG": "0.3392",
        "ABP": "70.795",
        "ECG": "0.48452"
    },
    {
        "PPG": "0.34702",
        "ABP": "70.209",
        "ECG": "0.52941"
    },
    {
        "PPG": "0.35777",
        "ABP": "69.622",
        "ECG": "0.62539"
    },
    {
        "PPG": "0.37341",
        "ABP": "69.035",
        "ECG": "0.45975"
    },
    {
        "PPG": "0.39101",
        "ABP": "68.644",
        "ECG": "0.22446"
    },
    {
        "PPG": "0.41056",
        "ABP": "68.253",
        "ECG": "0.14861"
    },
    {
        "PPG": "0.43206",
        "ABP": "68.057",
        "ECG": "0.23994"
    },
    {
        "PPG": "0.45455",
        "ABP": "67.862",
        "ECG": "0.36997"
    },
    {
        "PPG": "0.47801",
        "ABP": "67.862",
        "ECG": "0.4644"
    },
    {
        "PPG": "0.50244",
        "ABP": "67.666",
        "ECG": "0.48452"
    },
    {
        "PPG": "0.52688",
        "ABP": "67.666",
        "ECG": "0.51548"
    },
    {
        "PPG": "0.55034",
        "ABP": "67.666",
        "ECG": "0.5"
    },
    {
        "PPG": "0.56989",
        "ABP": "67.666",
        "ECG": "0.52012"
    },
    {
        "PPG": "0.58456",
        "ABP": "67.666",
        "ECG": "0.50929"
    },
    {
        "PPG": "0.59531",
        "ABP": "67.471",
        "ECG": "0.52477"
    },
    {
        "PPG": "0.60508",
        "ABP": "67.471",
        "ECG": "0.51548"
    },
    {
        "PPG": "0.6129",
        "ABP": "67.08",
        "ECG": "0.5356"
    },
    {
        "PPG": "0.61877",
        "ABP": "66.884",
        "ECG": "0.52012"
    },
    {
        "PPG": "0.62366",
        "ABP": "66.493",
        "ECG": "0.5356"
    },
    {
        "PPG": "0.62757",
        "ABP": "65.906",
        "ECG": "0.52941"
    },
    {
        "PPG": "0.63148",
        "ABP": "65.515",
        "ECG": "0.54954"
    },
    {
        "PPG": "0.63343",
        "ABP": "65.124",
        "ECG": "0.56037"
    },
    {
        "PPG": "0.63343",
        "ABP": "64.537",
        "ECG": "0.54489"
    },
    {
        "PPG": "0.63245",
        "ABP": "64.146",
        "ECG": "0.56966"
    },
    {
        "PPG": "0.62854",
        "ABP": "63.559",
        "ECG": "0.56502"
    },
    {
        "PPG": "0.62268",
        "ABP": "63.168",
        "ECG": "0.60991"
    },
    {
        "PPG": "0.61681",
        "ABP": "62.973",
        "ECG": "0.63003"
    },
    {
        "PPG": "0.61095",
        "ABP": "62.973",
        "ECG": "0.67028"
    },
    {
        "PPG": "0.60508",
        "ABP": "62.973",
        "ECG": "0.69505"
    },
    {
        "PPG": "0.59824",
        "ABP": "63.168",
        "ECG": "0.73065"
    },
    {
        "PPG": "0.59042",
        "ABP": "63.559",
        "ECG": "0.73529"
    },
    {
        "PPG": "0.5826",
        "ABP": "64.537",
        "ECG": "0.75077"
    },
    {
        "PPG": "0.57478",
        "ABP": "66.102",
        "ECG": "0.73065"
    },
    {
        "PPG": "0.56794",
        "ABP": "69.231",
        "ECG": "0.71517"
    },
    {
        "PPG": "0.56109",
        "ABP": "74.511",
        "ECG": "0.67028"
    },
    {
        "PPG": "0.55425",
        "ABP": "81.356",
        "ECG": "0.6548"
    },
    {
        "PPG": "0.54839",
        "ABP": "89.57",
        "ECG": "0.60526"
    },
    {
        "PPG": "0.54154",
        "ABP": "97.979",
        "ECG": "0.58978"
    },
    {
        "PPG": "0.5347",
        "ABP": "105.22",
        "ECG": "0.54954"
    },
    {
        "PPG": "0.52884",
        "ABP": "110.69",
        "ECG": "0.55573"
    },
    {
        "PPG": "0.52199",
        "ABP": "113.82",
        "ECG": "0.5356"
    },
    {
        "PPG": "0.51417",
        "ABP": "114.8",
        "ECG": "0.54025"
    },
    {
        "PPG": "0.50733",
        "ABP": "114.41",
        "ECG": "0.52477"
    },
    {
        "PPG": "0.50049",
        "ABP": "112.84",
        "ECG": "0.5356"
    },
    {
        "PPG": "0.4956",
        "ABP": "110.1",
        "ECG": "0.54025"
    },
    {
        "PPG": "0.49071",
        "ABP": "106.39",
        "ECG": "0.5356"
    },
    {
        "PPG": "0.4868",
        "ABP": "101.89",
        "ECG": "0.56966"
    },
    {
        "PPG": "0.48094",
        "ABP": "97.197",
        "ECG": "0.56502"
    },
    {
        "PPG": "0.47507",
        "ABP": "92.112",
        "ECG": "0.58978"
    },
    {
        "PPG": "0.46823",
        "ABP": "87.223",
        "ECG": "0.56966"
    },
    {
        "PPG": "0.46139",
        "ABP": "82.529",
        "ECG": "0.57585"
    },
    {
        "PPG": "0.45552",
        "ABP": "78.422",
        "ECG": "0.52941"
    },
    {
        "PPG": "0.44966",
        "ABP": "75.489",
        "ECG": "0.54025"
    },
    {
        "PPG": "0.44379",
        "ABP": "73.338",
        "ECG": "0.52477"
    },
    {
        "PPG": "0.43695",
        "ABP": "72.36",
        "ECG": "0.5356"
    },
    {
        "PPG": "0.43011",
        "ABP": "72.164",
        "ECG": "0.51548"
    },
    {
        "PPG": "0.42326",
        "ABP": "72.36",
        "ECG": "0.52012"
    },
    {
        "PPG": "0.4174",
        "ABP": "72.947",
        "ECG": "0.51548"
    },
    {
        "PPG": "0.41251",
        "ABP": "73.533",
        "ECG": "0.52477"
    },
    {
        "PPG": "0.40762",
        "ABP": "74.12",
        "ECG": "0.51548"
    },
    {
        "PPG": "0.40274",
        "ABP": "74.511",
        "ECG": "0.52012"
    },
    {
        "PPG": "0.39785",
        "ABP": "74.707",
        "ECG": "0.50929"
    },
    {
        "PPG": "0.39296",
        "ABP": "74.511",
        "ECG": "0.52941"
    },
    {
        "PPG": "0.39003",
        "ABP": "73.924",
        "ECG": "0.51548"
    },
    {
        "PPG": "0.38905",
        "ABP": "73.338",
        "ECG": "0.52941"
    },
    {
        "PPG": "0.38905",
        "ABP": "72.36",
        "ECG": "0.51548"
    },
    {
        "PPG": "0.39101",
        "ABP": "71.382",
        "ECG": "0.5356"
    },
    {
        "PPG": "0.39589",
        "ABP": "70.404",
        "ECG": "0.54025"
    },
    {
        "PPG": "0.40469",
        "ABP": "69.426",
        "ECG": "0.5805"
    },
    {
        "PPG": "0.41642",
        "ABP": "68.84",
        "ECG": "0.65015"
    },
    {
        "PPG": "0.43206",
        "ABP": "68.057",
        "ECG": "0.6904"
    },
    {
        "PPG": "0.45161",
        "ABP": "67.666",
        "ECG": "0.39009"
    },
    {
        "PPG": "0.4741",
        "ABP": "67.471",
        "ECG": "0.25387"
    },
    {
        "PPG": "0.49951",
        "ABP": "67.275",
        "ECG": "0.24923"
    },
    {
        "PPG": "0.5259",
        "ABP": "67.08",
        "ECG": "0.40402"
    },
    {
        "PPG": "0.54936",
        "ABP": "67.08",
        "ECG": "0.51548"
    },
    {
        "PPG": "0.56989",
        "ABP": "66.884",
        "ECG": "0.56037"
    },
    {
        "PPG": "0.59238",
        "ABP": "66.884",
        "ECG": "0.5805"
    },
    {
        "PPG": "0.61388",
        "ABP": "66.688",
        "ECG": "0.57585"
    },
    {
        "PPG": "0.63343",
        "ABP": "66.493",
        "ECG": "0.60062"
    },
    {
        "PPG": "0.65103",
        "ABP": "66.297",
        "ECG": "0.59598"
    },
    {
        "PPG": "0.66667",
        "ABP": "66.102",
        "ECG": "0.62074"
    },
    {
        "PPG": "0.68035",
        "ABP": "65.711",
        "ECG": "0.60991"
    },
    {
        "PPG": "0.69013",
        "ABP": "65.319",
        "ECG": "0.63003"
    },
    {
        "PPG": "0.69697",
        "ABP": "64.928",
        "ECG": "0.61455"
    },
    {
        "PPG": "0.70186",
        "ABP": "64.342",
        "ECG": "0.64087"
    },
    {
        "PPG": "0.70381",
        "ABP": "63.755",
        "ECG": "0.62539"
    },
    {
        "PPG": "0.70283",
        "ABP": "63.168",
        "ECG": "0.64551"
    },
    {
        "PPG": "0.70088",
        "ABP": "62.582",
        "ECG": "0.63467"
    },
    {
        "PPG": "0.69697",
        "ABP": "61.995",
        "ECG": "0.66099"
    },
    {
        "PPG": "0.69306",
        "ABP": "61.408",
        "ECG": "0.6548"
    },
    {
        "PPG": "0.68817",
        "ABP": "60.821",
        "ECG": "0.68111"
    },
    {
        "PPG": "0.68231",
        "ABP": "60.43",
        "ECG": "0.68111"
    },
    {
        "PPG": "0.67449",
        "ABP": "60.039",
        "ECG": "0.71981"
    },
    {
        "PPG": "0.66569",
        "ABP": "59.844",
        "ECG": "0.74613"
    },
    {
        "PPG": "0.65689",
        "ABP": "59.844",
        "ECG": "0.78638"
    },
    {
        "PPG": "0.64809",
        "ABP": "59.844",
        "ECG": "0.80495"
    },
    {
        "PPG": "0.6393",
        "ABP": "60.039",
        "ECG": "0.83591"
    },
    {
        "PPG": "0.62952",
        "ABP": "60.626",
        "ECG": "0.8452"
    },
    {
        "PPG": "0.61975",
        "ABP": "61.604",
        "ECG": "0.83127"
    },
    {
        "PPG": "0.61193",
        "ABP": "63.95",
        "ECG": "0.81115"
    },
    {
        "PPG": "0.60411",
        "ABP": "67.666",
        "ECG": "0.78638"
    },
    {
        "PPG": "0.59531",
        "ABP": "73.533",
        "ECG": "0.76006"
    },
    {
        "PPG": "0.58553",
        "ABP": "81.16",
        "ECG": "0.71981"
    },
    {
        "PPG": "0.57576",
        "ABP": "89.57",
        "ECG": "0.69505"
    },
    {
        "PPG": "0.56696",
        "ABP": "97.588",
        "ECG": "0.66099"
    },
    {
        "PPG": "0.55816",
        "ABP": "104.24",
        "ECG": "0.6548"
    },
    {
        "PPG": "0.54839",
        "ABP": "108.74",
        "ECG": "0.63467"
    },
    {
        "PPG": "0.53959",
        "ABP": "111.28",
        "ECG": "0.64087"
    },
    {
        "PPG": "0.52981",
        "ABP": "111.86",
        "ECG": "0.60991"
    },
    {
        "PPG": "0.52004",
        "ABP": "110.89",
        "ECG": "0.61455"
    },
    {
        "PPG": "0.51026",
        "ABP": "108.74",
        "ECG": "0.60062"
    },
    {
        "PPG": "0.50049",
        "ABP": "105.41",
        "ECG": "0.62539"
    },
    {
        "PPG": "0.49365",
        "ABP": "101.3",
        "ECG": "0.62074"
    },
    {
        "PPG": "0.4868",
        "ABP": "96.61",
        "ECG": "0.66099"
    },
    {
        "PPG": "0.47996",
        "ABP": "91.525",
        "ECG": "0.65015"
    },
    {
        "PPG": "0.47312",
        "ABP": "86.441",
        "ECG": "0.66099"
    },
    {
        "PPG": "0.46628",
        "ABP": "81.552",
        "ECG": "0.63003"
    },
    {
        "PPG": "0.45943",
        "ABP": "77.249",
        "ECG": "0.61455"
    },
    {
        "PPG": "0.45161",
        "ABP": "73.533",
        "ECG": "0.58978"
    },
    {
        "PPG": "0.44379",
        "ABP": "70.991",
        "ECG": "0.60062"
    },
    {
        "PPG": "0.435",
        "ABP": "69.231",
        "ECG": "0.57585"
    },
    {
        "PPG": "0.42522",
        "ABP": "68.449",
        "ECG": "0.56502"
    },
    {
        "PPG": "0.41642",
        "ABP": "68.449",
        "ECG": "0.56966"
    },
    {
        "PPG": "0.40762",
        "ABP": "69.035",
        "ECG": "0.54489"
    },
    {
        "PPG": "0.40078",
        "ABP": "69.622",
        "ECG": "0.55573"
    },
    {
        "PPG": "0.39492",
        "ABP": "70.6",
        "ECG": "0.54025"
    },
    {
        "PPG": "0.38612",
        "ABP": "71.186",
        "ECG": "0.54489"
    },
    {
        "PPG": "0.3783",
        "ABP": "71.969",
        "ECG": "0.52477"
    },
    {
        "PPG": "0.37048",
        "ABP": "72.36",
        "ECG": "0.5356"
    },
    {
        "PPG": "0.36266",
        "ABP": "72.36",
        "ECG": "0.51548"
    },
    {
        "PPG": "0.35484",
        "ABP": "72.164",
        "ECG": "0.52477"
    },
    {
        "PPG": "0.34897",
        "ABP": "71.969",
        "ECG": "0.51548"
    },
    {
        "PPG": "0.34604",
        "ABP": "71.186",
        "ECG": "0.52477"
    },
    {
        "PPG": "0.34506",
        "ABP": "70.6",
        "ECG": "0.51548"
    },
    {
        "PPG": "0.34897",
        "ABP": "69.622",
        "ECG": "0.54025"
    },
    {
        "PPG": "0.35679",
        "ABP": "69.035",
        "ECG": "0.56037"
    },
    {
        "PPG": "0.37048",
        "ABP": "68.253",
        "ECG": "0.66099"
    },
    {
        "PPG": "0.38514",
        "ABP": "67.471",
        "ECG": "0.56966"
    },
    {
        "PPG": "0.40176",
        "ABP": "66.884",
        "ECG": "0.31424"
    },
    {
        "PPG": "0.42229",
        "ABP": "66.493",
        "ECG": "0.18885"
    },
    {
        "PPG": "0.44575",
        "ABP": "66.102",
        "ECG": "0.24458"
    },
    {
        "PPG": "0.46921",
        "ABP": "65.906",
        "ECG": "0.37926"
    },
    {
        "PPG": "0.49365",
        "ABP": "65.711",
        "ECG": "0.50464"
    },
    {
        "PPG": "0.51808",
        "ABP": "65.515",
        "ECG": "0.5356"
    },
    {
        "PPG": "0.54154",
        "ABP": "65.515",
        "ECG": "0.56037"
    },
    {
        "PPG": "0.56305",
        "ABP": "65.319",
        "ECG": "0.56966"
    },
    {
        "PPG": "0.58358",
        "ABP": "65.319",
        "ECG": "0.56037"
    },
    {
        "PPG": "0.6002",
        "ABP": "65.124",
        "ECG": "0.5805"
    },
    {
        "PPG": "0.61388",
        "ABP": "64.928",
        "ECG": "0.56502"
    },
    {
        "PPG": "0.62463",
        "ABP": "64.733",
        "ECG": "0.58514"
    },
    {
        "PPG": "0.6305",
        "ABP": "64.537",
        "ECG": "0.57585"
    },
    {
        "PPG": "0.63441",
        "ABP": "64.146",
        "ECG": "0.59598"
    },
    {
        "PPG": "0.63636",
        "ABP": "63.755",
        "ECG": "0.58514"
    },
    {
        "PPG": "0.63636",
        "ABP": "63.364",
        "ECG": "0.60062"
    },
    {
        "PPG": "0.63539",
        "ABP": "62.973",
        "ECG": "0.58978"
    },
    {
        "PPG": "0.63343",
        "ABP": "62.386",
        "ECG": "0.60991"
    },
    {
        "PPG": "0.63148",
        "ABP": "61.604",
        "ECG": "0.60062"
    },
    {
        "PPG": "0.62952",
        "ABP": "61.213",
        "ECG": "0.63003"
    },
    {
        "PPG": "0.62561",
        "ABP": "60.626",
        "ECG": "0.62074"
    },
    {
        "PPG": "0.62072",
        "ABP": "60.039",
        "ECG": "0.66099"
    },
    {
        "PPG": "0.61388",
        "ABP": "59.648",
        "ECG": "0.67492"
    },
    {
        "PPG": "0.60704",
        "ABP": "59.452",
        "ECG": "0.71981"
    },
    {
        "PPG": "0.60117",
        "ABP": "59.452",
        "ECG": "0.73065"
    },
    {
        "PPG": "0.59335",
        "ABP": "59.452",
        "ECG": "0.77554"
    },
    {
        "PPG": "0.58358",
        "ABP": "59.844",
        "ECG": "0.77554"
    },
    {
        "PPG": "0.5738",
        "ABP": "60.43",
        "ECG": "0.80031"
    },
    {
        "PPG": "0.56403",
        "ABP": "61.604",
        "ECG": "0.77554"
    },
    {
        "PPG": "0.55425",
        "ABP": "63.95",
        "ECG": "0.7709"
    },
    {
        "PPG": "0.54448",
        "ABP": "67.666",
        "ECG": "0.72601"
    },
    {
        "PPG": "0.53568",
        "ABP": "73.338",
        "ECG": "0.70588"
    },
    {
        "PPG": "0.52786",
        "ABP": "80.574",
        "ECG": "0.6548"
    },
    {
        "PPG": "0.51906",
        "ABP": "88.592",
        "ECG": "0.63467"
    },
    {
        "PPG": "0.51026",
        "ABP": "96.219",
        "ECG": "0.60526"
    },
    {
        "PPG": "0.50244",
        "ABP": "102.48",
        "ECG": "0.58978"
    },
    {
        "PPG": "0.49658",
        "ABP": "106.98",
        "ECG": "0.57585"
    },
    {
        "PPG": "0.49071",
        "ABP": "109.52",
        "ECG": "0.56502"
    },
    {
        "PPG": "0.48485",
        "ABP": "110.3",
        "ECG": "0.56037"
    },
    {
        "PPG": "0.47801",
        "ABP": "109.52",
        "ECG": "0.54954"
    },
    {
        "PPG": "0.47116",
        "ABP": "107.56",
        "ECG": "0.56502"
    },
    {
        "PPG": "0.46334",
        "ABP": "104.43",
        "ECG": "0.54954"
    },
    {
        "PPG": "0.4565",
        "ABP": "100.52",
        "ECG": "0.5805"
    },
    {
        "PPG": "0.44966",
        "ABP": "95.828",
        "ECG": "0.5805"
    },
    {
        "PPG": "0.44184",
        "ABP": "90.743",
        "ECG": "0.58978"
    },
    {
        "PPG": "0.435",
        "ABP": "85.658",
        "ECG": "0.56502"
    },
    {
        "PPG": "0.42717",
        "ABP": "80.769",
        "ECG": "0.56966"
    },
    {
        "PPG": "0.41935",
        "ABP": "76.467",
        "ECG": "0.52012"
    },
    {
        "PPG": "0.41349",
        "ABP": "72.751",
        "ECG": "0.5356"
    },
    {
        "PPG": "0.40958",
        "ABP": "70.209",
        "ECG": "0.51548"
    },
    {
        "PPG": "0.40567",
        "ABP": "68.84",
        "ECG": "0.50929"
    },
    {
        "PPG": "0.40078",
        "ABP": "68.057",
        "ECG": "0.48452"
    },
    {
        "PPG": "0.39296",
        "ABP": "68.253",
        "ECG": "0.5"
    },
    {
        "PPG": "0.38514",
        "ABP": "68.644",
        "ECG": "0.47523"
    },
    {
        "PPG": "0.37732",
        "ABP": "69.426",
        "ECG": "0.49071"
    },
    {
        "PPG": "0.3695",
        "ABP": "70.209",
        "ECG": "0.47059"
    },
    {
        "PPG": "0.36168",
        "ABP": "70.795",
        "ECG": "0.47988"
    },
    {
        "PPG": "0.35484",
        "ABP": "71.578",
        "ECG": "0.4644"
    },
    {
        "PPG": "0.348",
        "ABP": "71.773",
        "ECG": "0.47523"
    },
    {
        "PPG": "0.34311",
        "ABP": "71.969",
        "ECG": "0.4644"
    },
    {
        "PPG": "0.34018",
        "ABP": "71.578",
        "ECG": "0.45975"
    },
    {
        "PPG": "0.33822",
        "ABP": "71.186",
        "ECG": "0.4644"
    },
    {
        "PPG": "0.33822",
        "ABP": "70.404",
        "ECG": "0.45046"
    },
    {
        "PPG": "0.3392",
        "ABP": "69.622",
        "ECG": "0.47059"
    },
    {
        "PPG": "0.34213",
        "ABP": "69.035",
        "ECG": "0.4644"
    },
    {
        "PPG": "0.34897",
        "ABP": "68.253",
        "ECG": "0.5356"
    },
    {
        "PPG": "0.35973",
        "ABP": "67.471",
        "ECG": "0.60062"
    },
    {
        "PPG": "0.37537",
        "ABP": "66.884",
        "ECG": "0.43034"
    },
    {
        "PPG": "0.39492",
        "ABP": "66.493",
        "ECG": "0.17492"
    },
    {
        "PPG": "0.41544",
        "ABP": "66.102",
        "ECG": "0.13932"
    },
    {
        "PPG": "0.43793",
        "ABP": "65.906",
        "ECG": "0.20898"
    },
    {
        "PPG": "0.46237",
        "ABP": "65.906",
        "ECG": "0.36997"
    },
    {
        "PPG": "0.4868",
        "ABP": "65.711",
        "ECG": "0.43963"
    },
    {
        "PPG": "0.51026",
        "ABP": "65.711",
        "ECG": "0.48452"
    },
    {
        "PPG": "0.53177",
        "ABP": "65.711",
        "ECG": "0.47988"
    },
    {
        "PPG": "0.54936",
        "ABP": "65.711",
        "ECG": "0.50464"
    },
    {
        "PPG": "0.56696",
        "ABP": "65.711",
        "ECG": "0.49071"
    },
    {
        "PPG": "0.5826",
        "ABP": "65.711",
        "ECG": "0.50929"
    },
    {
        "PPG": "0.59531",
        "ABP": "65.515",
        "ECG": "0.49536"
    },
    {
        "PPG": "0.60704",
        "ABP": "65.319",
        "ECG": "0.50929"
    },
    {
        "PPG": "0.61584",
        "ABP": "65.124",
        "ECG": "0.49536"
    },
    {
        "PPG": "0.62268",
        "ABP": "64.928",
        "ECG": "0.50929"
    },
    {
        "PPG": "0.62659",
        "ABP": "64.733",
        "ECG": "0.49536"
    },
    {
        "PPG": "0.62854",
        "ABP": "64.537",
        "ECG": "0.50929"
    },
    {
        "PPG": "0.62757",
        "ABP": "64.146",
        "ECG": "0.5"
    },
    {
        "PPG": "0.62659",
        "ABP": "63.559",
        "ECG": "0.51548"
    },
    {
        "PPG": "0.62463",
        "ABP": "63.168",
        "ECG": "0.52012"
    },
    {
        "PPG": "0.6217",
        "ABP": "62.777",
        "ECG": "0.51548"
    },
    {
        "PPG": "0.61877",
        "ABP": "62.19",
        "ECG": "0.54489"
    },
    {
        "PPG": "0.61486",
        "ABP": "61.799",
        "ECG": "0.56966"
    },
    {
        "PPG": "0.60899",
        "ABP": "61.604",
        "ECG": "0.59598"
    },
    {
        "PPG": "0.60215",
        "ABP": "61.604",
        "ECG": "0.62074"
    },
    {
        "PPG": "0.59531",
        "ABP": "61.604",
        "ECG": "0.6548"
    },
    {
        "PPG": "0.58651",
        "ABP": "61.799",
        "ECG": "0.66563"
    },
    {
        "PPG": "0.57771",
        "ABP": "62.19",
        "ECG": "0.68576"
    },
    {
        "PPG": "0.56794",
        "ABP": "62.973",
        "ECG": "0.68111"
    },
    {
        "PPG": "0.56012",
        "ABP": "64.733",
        "ECG": "0.67492"
    },
    {
        "PPG": "0.5523",
        "ABP": "67.666",
        "ECG": "0.64087"
    },
    {
        "PPG": "0.54448",
        "ABP": "72.555",
        "ECG": "0.62074"
    },
    {
        "PPG": "0.53861",
        "ABP": "79.205",
        "ECG": "0.56502"
    },
    {
        "PPG": "0.53177",
        "ABP": "87.027",
        "ECG": "0.54954"
    },
    {
        "PPG": "0.52297",
        "ABP": "95.046",
        "ECG": "0.50929"
    },
    {
        "PPG": "0.51417",
        "ABP": "102.28",
        "ECG": "0.5"
    },
    {
        "PPG": "0.50538",
        "ABP": "107.95",
        "ECG": "0.47059"
    },
    {
        "PPG": "0.49658",
        "ABP": "111.47",
        "ECG": "0.47523"
    },
    {
        "PPG": "0.48876",
        "ABP": "113.04",
        "ECG": "0.45511"
    },
    {
        "PPG": "0.48192",
        "ABP": "113.04",
        "ECG": "0.4644"
    },
    {
        "PPG": "0.47605",
        "ABP": "111.86",
        "ECG": "0.44427"
    },
    {
        "PPG": "0.47116",
        "ABP": "109.32",
        "ECG": "0.4644"
    },
    {
        "PPG": "0.46725",
        "ABP": "105.8",
        "ECG": "0.47059"
    },
    {
        "PPG": "0.46334",
        "ABP": "101.5",
        "ECG": "0.5"
    },
    {
        "PPG": "0.46041",
        "ABP": "96.806",
        "ECG": "0.50464"
    },
    {
        "PPG": "0.45748",
        "ABP": "91.917",
        "ECG": "0.49536"
    },
    {
        "PPG": "0.45259",
        "ABP": "87.027",
        "ECG": "0.5"
    },
    {
        "PPG": "0.44575",
        "ABP": "82.529",
        "ECG": "0.47059"
    },
    {
        "PPG": "0.43891",
        "ABP": "78.422",
        "ECG": "0.45046"
    },
    {
        "PPG": "0.42815",
        "ABP": "75.489",
        "ECG": "0.44427"
    },
    {
        "PPG": "0.41642",
        "ABP": "73.533",
        "ECG": "0.45046"
    },
    {
        "PPG": "0.40762",
        "ABP": "72.555",
        "ECG": "0.41486"
    },
    {
        "PPG": "0.40176",
        "ABP": "72.36",
        "ECG": "0.42415"
    },
    {
        "PPG": "0.39589",
        "ABP": "72.751",
        "ECG": "0.39938"
    },
    {
        "PPG": "0.39101",
        "ABP": "73.533",
        "ECG": "0.41022"
    },
    {
        "PPG": "0.38612",
        "ABP": "74.12",
        "ECG": "0.39474"
    },
    {
        "PPG": "0.38025",
        "ABP": "74.902",
        "ECG": "0.40402"
    },
    {
        "PPG": "0.37439",
        "ABP": "75.685",
        "ECG": "0.38545"
    },
    {
        "PPG": "0.3695",
        "ABP": "76.076",
        "ECG": "0.39938"
    },
    {
        "PPG": "0.36364",
        "ABP": "76.271",
        "ECG": "0.37926"
    },
    {
        "PPG": "0.35679",
        "ABP": "76.271",
        "ECG": "0.39938"
    },
    {
        "PPG": "0.35191",
        "ABP": "75.88",
        "ECG": "0.37926"
    },
    {
        "PPG": "0.34897",
        "ABP": "75.293",
        "ECG": "0.39938"
    },
    {
        "PPG": "0.34897",
        "ABP": "74.511",
        "ECG": "0.38545"
    },
    {
        "PPG": "0.35191",
        "ABP": "73.924",
        "ECG": "0.4195"
    },
    {
        "PPG": "0.3607",
        "ABP": "73.142",
        "ECG": "0.43034"
    },
    {
        "PPG": "0.37243",
        "ABP": "72.555",
        "ECG": "0.54025"
    },
    {
        "PPG": "0.3871",
        "ABP": "71.969",
        "ECG": "0.5805"
    },
    {
        "PPG": "0.40371",
        "ABP": "71.382",
        "ECG": "0.28947"
    },
    {
        "PPG": "0.42033",
        "ABP": "70.991",
        "ECG": "0.13932"
    },
    {
        "PPG": "0.43891",
        "ABP": "70.6",
        "ECG": "0.12384"
    },
    {
        "PPG": "0.46041",
        "ABP": "70.404",
        "ECG": "0.28947"
    },
    {
        "PPG": "0.48485",
        "ABP": "70.209",
        "ECG": "0.39474"
    },
    {
        "PPG": "0.50929",
        "ABP": "70.209",
        "ECG": "0.44427"
    },
    {
        "PPG": "0.53372",
        "ABP": "70.013",
        "ECG": "0.45511"
    },
    {
        "PPG": "0.55816",
        "ABP": "70.013",
        "ECG": "0.47059"
    },
    {
        "PPG": "0.57869",
        "ABP": "69.818",
        "ECG": "0.47523"
    },
    {
        "PPG": "0.59726",
        "ABP": "69.622",
        "ECG": "0.49071"
    },
    {
        "PPG": "0.6129",
        "ABP": "69.426",
        "ECG": "0.48452"
    },
    {
        "PPG": "0.62561",
        "ABP": "69.035",
        "ECG": "0.50464"
    },
    {
        "PPG": "0.63539",
        "ABP": "68.84",
        "ECG": "0.5"
    },
    {
        "PPG": "0.64125",
        "ABP": "68.449",
        "ECG": "0.52941"
    },
    {
        "PPG": "0.64516",
        "ABP": "67.862",
        "ECG": "0.52012"
    },
    {
        "PPG": "0.64712",
        "ABP": "67.471",
        "ECG": "0.54025"
    },
    {
        "PPG": "0.64809",
        "ABP": "66.884",
        "ECG": "0.5356"
    },
    {
        "PPG": "0.64907",
        "ABP": "66.102",
        "ECG": "0.55573"
    },
    {
        "PPG": "0.64809",
        "ABP": "65.515",
        "ECG": "0.54954"
    },
    {
        "PPG": "0.64516",
        "ABP": "64.733",
        "ECG": "0.57585"
    },
    {
        "PPG": "0.64223",
        "ABP": "63.95",
        "ECG": "0.5805"
    },
    {
        "PPG": "0.63832",
        "ABP": "63.364",
        "ECG": "0.61455"
    },
    {
        "PPG": "0.63343",
        "ABP": "62.777",
        "ECG": "0.62539"
    },
    {
        "PPG": "0.62854",
        "ABP": "61.995",
        "ECG": "0.67028"
    },
    {
        "PPG": "0.62268",
        "ABP": "61.604",
        "ECG": "0.6904"
    },
    {
        "PPG": "0.61486",
        "ABP": "61.213",
        "ECG": "0.73065"
    },
    {
        "PPG": "0.60899",
        "ABP": "61.213",
        "ECG": "0.74613"
    },
    {
        "PPG": "0.60411",
        "ABP": "61.408",
        "ECG": "0.76006"
    },
    {
        "PPG": "0.59922",
        "ABP": "62.582",
        "ECG": "0.76625"
    },
    {
        "PPG": "0.59335",
        "ABP": "64.928",
        "ECG": "0.73529"
    },
    {
        "PPG": "0.58749",
        "ABP": "69.035",
        "ECG": "0.70588"
    },
    {
        "PPG": "0.58065",
        "ABP": "75.293",
        "ECG": "0.67028"
    },
    {
        "PPG": "0.57478",
        "ABP": "83.507",
        "ECG": "0.64087"
    },
    {
        "PPG": "0.56794",
        "ABP": "92.112",
        "ECG": "0.60991"
    },
    {
        "PPG": "0.56109",
        "ABP": "100.33",
        "ECG": "0.58978"
    },
    {
        "PPG": "0.55425",
        "ABP": "106.78",
        "ECG": "0.56502"
    },
    {
        "PPG": "0.54741",
        "ABP": "111.28",
        "ECG": "0.56037"
    },
    {
        "PPG": "0.54057",
        "ABP": "113.43",
        "ECG": "0.54025"
    },
    {
        "PPG": "0.53568",
        "ABP": "113.82",
        "ECG": "0.55573"
    },
    {
        "PPG": "0.53079",
        "ABP": "112.65",
        "ECG": "0.5356"
    },
    {
        "PPG": "0.52493",
        "ABP": "110.1",
        "ECG": "0.54954"
    },
    {
        "PPG": "0.51906",
        "ABP": "106.58",
        "ECG": "0.54025"
    },
    {
        "PPG": "0.51222",
        "ABP": "102.48",
        "ECG": "0.56966"
    },
    {
        "PPG": "0.50635",
        "ABP": "97.588",
        "ECG": "0.57585"
    },
    {
        "PPG": "0.49951",
        "ABP": "92.503",
        "ECG": "0.60062"
    },
    {
        "PPG": "0.49267",
        "ABP": "87.419",
        "ECG": "0.58514"
    },
    {
        "PPG": "0.4868",
        "ABP": "82.529",
        "ECG": "0.58978"
    },
    {
        "PPG": "0.48094",
        "ABP": "78.227",
        "ECG": "0.54954"
    },
    {
        "PPG": "0.4741",
        "ABP": "74.511",
        "ECG": "0.54025"
    },
    {
        "PPG": "0.46725",
        "ABP": "71.773",
        "ECG": "0.54489"
    },
    {
        "PPG": "0.46041",
        "ABP": "70.013",
        "ECG": "0.52941"
    },
    {
        "PPG": "0.45552",
        "ABP": "69.035",
        "ECG": "0.50929"
    },
    {
        "PPG": "0.45064",
        "ABP": "69.035",
        "ECG": "0.50464"
    },
    {
        "PPG": "0.44379",
        "ABP": "69.426",
        "ECG": "0.51548"
    },
    {
        "PPG": "0.43597",
        "ABP": "70.013",
        "ECG": "0.5"
    },
    {
        "PPG": "0.4262",
        "ABP": "70.991",
        "ECG": "0.51548"
    },
    {
        "PPG": "0.4174",
        "ABP": "71.773",
        "ECG": "0.5"
    },
    {
        "PPG": "0.4086",
        "ABP": "72.36",
        "ECG": "0.50929"
    },
    {
        "PPG": "0.40078",
        "ABP": "72.947",
        "ECG": "0.49536"
    },
    {
        "PPG": "0.39492",
        "ABP": "73.142",
        "ECG": "0.51548"
    },
    {
        "PPG": "0.38905",
        "ABP": "72.947",
        "ECG": "0.49536"
    },
    {
        "PPG": "0.38514",
        "ABP": "72.555",
        "ECG": "0.50929"
    },
    {
        "PPG": "0.38514",
        "ABP": "71.969",
        "ECG": "0.49536"
    },
    {
        "PPG": "0.38807",
        "ABP": "71.186",
        "ECG": "0.50929"
    },
    {
        "PPG": "0.39394",
        "ABP": "70.404",
        "ECG": "0.51548"
    },
    {
        "PPG": "0.40176",
        "ABP": "69.426",
        "ECG": "0.56966"
    },
    {
        "PPG": "0.41251",
        "ABP": "68.84",
        "ECG": "0.64551"
    },
    {
        "PPG": "0.4262",
        "ABP": "68.057",
        "ECG": "0.56037"
    },
    {
        "PPG": "0.44282",
        "ABP": "67.471",
        "ECG": "0.28483"
    },
    {
        "PPG": "0.46041",
        "ABP": "67.08",
        "ECG": "0.19969"
    },
    {
        "PPG": "0.47996",
        "ABP": "66.688",
        "ECG": "0.23375"
    },
    {
        "PPG": "0.50147",
        "ABP": "66.297",
        "ECG": "0.39474"
    },
    {
        "PPG": "0.52199",
        "ABP": "66.297",
        "ECG": "0.47988"
    },
    {
        "PPG": "0.54252",
        "ABP": "66.102",
        "ECG": "0.5356"
    },
    {
        "PPG": "0.56305",
        "ABP": "65.906",
        "ECG": "0.54025"
    },
    {
        "PPG": "0.58065",
        "ABP": "65.906",
        "ECG": "0.56502"
    },
    {
        "PPG": "0.59531",
        "ABP": "65.906",
        "ECG": "0.56037"
    },
    {
        "PPG": "0.60704",
        "ABP": "65.711",
        "ECG": "0.5805"
    },
    {
        "PPG": "0.61779",
        "ABP": "65.515",
        "ECG": "0.56966"
    },
    {
        "PPG": "0.62659",
        "ABP": "65.319",
        "ECG": "0.5805"
    },
    {
        "PPG": "0.63245",
        "ABP": "64.928",
        "ECG": "0.58978"
    },
    {
        "PPG": "0.63539",
        "ABP": "64.537",
        "ECG": "0.5805"
    },
    {
        "PPG": "0.63636",
        "ABP": "64.342",
        "ECG": "0.59598"
    },
    {
        "PPG": "0.63539",
        "ABP": "63.755",
        "ECG": "0.58978"
    },
    {
        "PPG": "0.63245",
        "ABP": "63.364",
        "ECG": "0.60526"
    },
    {
        "PPG": "0.62757",
        "ABP": "62.777",
        "ECG": "0.59598"
    },
    {
        "PPG": "0.6217",
        "ABP": "62.19",
        "ECG": "0.62074"
    },
    {
        "PPG": "0.61486",
        "ABP": "61.604",
        "ECG": "0.60991"
    },
    {
        "PPG": "0.60899",
        "ABP": "61.017",
        "ECG": "0.65015"
    },
    {
        "PPG": "0.60313",
        "ABP": "60.43",
        "ECG": "0.66099"
    },
    {
        "PPG": "0.59629",
        "ABP": "60.039",
        "ECG": "0.69969"
    },
    {
        "PPG": "0.59042",
        "ABP": "59.844",
        "ECG": "0.71517"
    },
    {
        "PPG": "0.58358",
        "ABP": "59.844",
        "ECG": "0.76006"
    },
    {
        "PPG": "0.57576",
        "ABP": "59.844",
        "ECG": "0.77554"
    },
    {
        "PPG": "0.56794",
        "ABP": "60.039",
        "ECG": "0.80495"
    },
    {
        "PPG": "0.55914",
        "ABP": "60.821",
        "ECG": "0.79567"
    },
    {
        "PPG": "0.54936",
        "ABP": "61.995",
        "ECG": "0.80031"
    },
    {
        "PPG": "0.54057",
        "ABP": "64.537",
        "ECG": "0.7709"
    },
    {
        "PPG": "0.53079",
        "ABP": "68.644",
        "ECG": "0.75077"
    },
    {
        "PPG": "0.52199",
        "ABP": "74.511",
        "ECG": "0.71053"
    },
    {
        "PPG": "0.5132",
        "ABP": "81.943",
        "ECG": "0.68576"
    },
    {
        "PPG": "0.50538",
        "ABP": "89.961",
        "ECG": "0.64551"
    },
    {
        "PPG": "0.49756",
        "ABP": "97.588",
        "ECG": "0.63467"
    },
    {
        "PPG": "0.49071",
        "ABP": "103.65",
        "ECG": "0.60526"
    },
    {
        "PPG": "0.48387",
        "ABP": "107.95",
        "ECG": "0.60062"
    },
    {
        "PPG": "0.47703",
        "ABP": "110.3",
        "ECG": "0.60526"
    },
    {
        "PPG": "0.47019",
        "ABP": "110.89",
        "ECG": "0.58514"
    },
    {
        "PPG": "0.46334",
        "ABP": "109.91",
        "ECG": "0.58978"
    },
    {
        "PPG": "0.4565",
        "ABP": "107.76",
        "ECG": "0.57585"
    },
    {
        "PPG": "0.44966",
        "ABP": "104.43",
        "ECG": "0.58978"
    },
    {
        "PPG": "0.44282",
        "ABP": "100.52",
        "ECG": "0.58514"
    },
    {
        "PPG": "0.43597",
        "ABP": "95.828",
        "ECG": "0.61455"
    },
    {
        "PPG": "0.43011",
        "ABP": "90.743",
        "ECG": "0.60991"
    },
    {
        "PPG": "0.42424",
        "ABP": "85.658",
        "ECG": "0.61455"
    },
    {
        "PPG": "0.41935",
        "ABP": "80.769",
        "ECG": "0.58978"
    },
    {
        "PPG": "0.41349",
        "ABP": "76.467",
        "ECG": "0.56966"
    },
    {
        "PPG": "0.40762",
        "ABP": "73.142",
        "ECG": "0.54954"
    },
    {
        "PPG": "0.40274",
        "ABP": "70.6",
        "ECG": "0.56502"
    },
    {
        "PPG": "0.39687",
        "ABP": "69.035",
        "ECG": "0.52477"
    },
    {
        "PPG": "0.39198",
        "ABP": "68.449",
        "ECG": "0.5356"
    },
    {
        "PPG": "0.38612",
        "ABP": "68.644",
        "ECG": "0.51548"
    },
    {
        "PPG": "0.38025",
        "ABP": "69.035",
        "ECG": "0.52477"
    },
    {
        "PPG": "0.37341",
        "ABP": "69.818",
        "ECG": "0.50929"
    },
    {
        "PPG": "0.36461",
        "ABP": "70.6",
        "ECG": "0.52012"
    },
    {
        "PPG": "0.35679",
        "ABP": "71.382",
        "ECG": "0.5"
    },
    {
        "PPG": "0.348",
        "ABP": "71.969",
        "ECG": "0.51548"
    },
    {
        "PPG": "0.34115",
        "ABP": "72.164",
        "ECG": "0.50464"
    },
    {
        "PPG": "0.33529",
        "ABP": "72.36",
        "ECG": "0.51548"
    },
    {
        "PPG": "0.33138",
        "ABP": "71.969",
        "ECG": "0.50464"
    },
    {
        "PPG": "0.32845",
        "ABP": "71.578",
        "ECG": "0.51548"
    },
    {
        "PPG": "0.32747",
        "ABP": "70.795",
        "ECG": "0.50464"
    },
    {
        "PPG": "0.32845",
        "ABP": "70.209",
        "ECG": "0.5"
    },
    {
        "PPG": "0.33333",
        "ABP": "69.426",
        "ECG": "0.5356"
    },
    {
        "PPG": "0.34018",
        "ABP": "68.644",
        "ECG": "0.52941"
    },
    {
        "PPG": "0.35191",
        "ABP": "67.862",
        "ECG": "0.65015"
    },
    {
        "PPG": "0.36657",
        "ABP": "67.471",
        "ECG": "0.47523"
    },
    {
        "PPG": "0.38319",
        "ABP": "66.884",
        "ECG": "0.23375"
    },
    {
        "PPG": "0.40078",
        "ABP": "66.493",
        "ECG": "0.18421"
    },
    {
        "PPG": "0.41838",
        "ABP": "66.102",
        "ECG": "0.27399"
    },
    {
        "PPG": "0.43597",
        "ABP": "65.906",
        "ECG": "0.41486"
    },
    {
        "PPG": "0.4565",
        "ABP": "65.906",
        "ECG": "0.50929"
    },
    {
        "PPG": "0.47801",
        "ABP": "65.906",
        "ECG": "0.52477"
    },
    {
        "PPG": "0.50049",
        "ABP": "65.711",
        "ECG": "0.54954"
    },
    {
        "PPG": "0.52102",
        "ABP": "65.711",
        "ECG": "0.54025"
    },
    {
        "PPG": "0.54057",
        "ABP": "65.515",
        "ECG": "0.57585"
    },
    {
        "PPG": "0.55621",
        "ABP": "65.319",
        "ECG": "0.56037"
    },
    {
        "PPG": "0.56891",
        "ABP": "65.124",
        "ECG": "0.58514"
    },
    {
        "PPG": "0.57967",
        "ABP": "64.733",
        "ECG": "0.56502"
    },
    {
        "PPG": "0.58749",
        "ABP": "64.537",
        "ECG": "0.58978"
    },
    {
        "PPG": "0.59335",
        "ABP": "64.146",
        "ECG": "0.56502"
    },
    {
        "PPG": "0.59726",
        "ABP": "63.755",
        "ECG": "0.58978"
    },
    {
        "PPG": "0.59922",
        "ABP": "63.168",
        "ECG": "0.56966"
    },
    {
        "PPG": "0.59922",
        "ABP": "62.777",
        "ECG": "0.59598"
    },
    {
        "PPG": "0.59824",
        "ABP": "62.19",
        "ECG": "0.58978"
    },
    {
        "PPG": "0.59629",
        "ABP": "61.604",
        "ECG": "0.60991"
    },
    {
        "PPG": "0.59433",
        "ABP": "61.017",
        "ECG": "0.62074"
    },
    {
        "PPG": "0.58944",
        "ABP": "60.626",
        "ECG": "0.64087"
    },
    {
        "PPG": "0.58456",
        "ABP": "60.039",
        "ECG": "0.6548"
    },
    {
        "PPG": "0.57869",
        "ABP": "59.844",
        "ECG": "0.68576"
    },
    {
        "PPG": "0.57185",
        "ABP": "59.648",
        "ECG": "0.71053"
    },
    {
        "PPG": "0.565",
        "ABP": "59.648",
        "ECG": "0.74613"
    },
    {
        "PPG": "0.55816",
        "ABP": "59.648",
        "ECG": "0.77554"
    },
    {
        "PPG": "0.55034",
        "ABP": "60.039",
        "ECG": "0.78638"
    },
    {
        "PPG": "0.5435",
        "ABP": "60.821",
        "ECG": "0.80031"
    },
    {
        "PPG": "0.53763",
        "ABP": "62.386",
        "ECG": "0.77554"
    },
    {
        "PPG": "0.52981",
        "ABP": "65.124",
        "ECG": "0.75542"
    },
    {
        "PPG": "0.52102",
        "ABP": "69.622",
        "ECG": "0.71053"
    },
    {
        "PPG": "0.5132",
        "ABP": "75.88",
        "ECG": "0.68576"
    },
    {
        "PPG": "0.50635",
        "ABP": "83.507",
        "ECG": "0.63467"
    },
    {
        "PPG": "0.49853",
        "ABP": "91.525",
        "ECG": "0.62539"
    },
    {
        "PPG": "0.48974",
        "ABP": "98.761",
        "ECG": "0.5805"
    },
    {
        "PPG": "0.48192",
        "ABP": "104.63",
        "ECG": "0.5805"
    },
    {
        "PPG": "0.47507",
        "ABP": "108.54",
        "ECG": "0.54489"
    },
    {
        "PPG": "0.46823",
        "ABP": "110.5",
        "ECG": "0.56037"
    },
    {
        "PPG": "0.46139",
        "ABP": "110.89",
        "ECG": "0.52941"
    },
    {
        "PPG": "0.45455",
        "ABP": "109.71",
        "ECG": "0.54489"
    },
    {
        "PPG": "0.44868",
        "ABP": "107.37",
        "ECG": "0.52477"
    },
    {
        "PPG": "0.44379",
        "ABP": "104.04",
        "ECG": "0.56037"
    },
    {
        "PPG": "0.43793",
        "ABP": "99.935",
        "ECG": "0.55573"
    },
    {
        "PPG": "0.43109",
        "ABP": "95.437",
        "ECG": "0.57585"
    },
    {
        "PPG": "0.42522",
        "ABP": "90.548",
        "ECG": "0.55573"
    },
    {
        "PPG": "0.41838",
        "ABP": "85.658",
        "ECG": "0.56037"
    },
    {
        "PPG": "0.41153",
        "ABP": "81.16",
        "ECG": "0.52477"
    },
    {
        "PPG": "0.40567",
        "ABP": "77.054",
        "ECG": "0.5"
    },
    {
        "PPG": "0.40078",
        "ABP": "73.924",
        "ECG": "0.51548"
    },
    {
        "PPG": "0.39589",
        "ABP": "71.773",
        "ECG": "0.49536"
    },
    {
        "PPG": "0.39003",
        "ABP": "70.6",
        "ECG": "0.47988"
    },
    {
        "PPG": "0.38319",
        "ABP": "70.209",
        "ECG": "0.4644"
    },
    {
        "PPG": "0.3783",
        "ABP": "70.6",
        "ECG": "0.47988"
    },
    {
        "PPG": "0.37341",
        "ABP": "70.991",
        "ECG": "0.45046"
    },
    {
        "PPG": "0.36657",
        "ABP": "71.969",
        "ECG": "0.47059"
    },
    {
        "PPG": "0.35875",
        "ABP": "72.751",
        "ECG": "0.44427"
    },
    {
        "PPG": "0.35191",
        "ABP": "73.338",
        "ECG": "0.45975"
    },
    {
        "PPG": "0.34506",
        "ABP": "73.924",
        "ECG": "0.43963"
    },
    {
        "PPG": "0.34018",
        "ABP": "74.12",
        "ECG": "0.45975"
    },
    {
        "PPG": "0.33529",
        "ABP": "74.12",
        "ECG": "0.43963"
    },
    {
        "PPG": "0.33236",
        "ABP": "73.924",
        "ECG": "0.4644"
    },
    {
        "PPG": "0.3304",
        "ABP": "73.338",
        "ECG": "0.43963"
    },
    {
        "PPG": "0.3304",
        "ABP": "72.751",
        "ECG": "0.4644"
    },
    {
        "PPG": "0.33333",
        "ABP": "72.164",
        "ECG": "0.45046"
    },
    {
        "PPG": "0.3392",
        "ABP": "71.578",
        "ECG": "0.5"
    },
    {
        "PPG": "0.34702",
        "ABP": "70.795",
        "ECG": "0.55573"
    },
    {
        "PPG": "0.35679",
        "ABP": "70.209",
        "ECG": "0.60526"
    },
    {
        "PPG": "0.37048",
        "ABP": "69.818",
        "ECG": "0.31889"
    },
    {
        "PPG": "0.38807",
        "ABP": "69.426",
        "ECG": "0.17957"
    },
    {
        "PPG": "0.40762",
        "ABP": "69.231",
        "ECG": "0.15944"
    },
    {
        "PPG": "0.43011",
        "ABP": "69.035",
        "ECG": "0.3096"
    },
    {
        "PPG": "0.45259",
        "ABP": "68.84",
        "ECG": "0.41486"
    },
    {
        "PPG": "0.47507",
        "ABP": "68.84",
        "ECG": "0.47523"
    },
    {
        "PPG": "0.49853",
        "ABP": "68.84",
        "ECG": "0.49536"
    },
    {
        "PPG": "0.52102",
        "ABP": "68.84",
        "ECG": "0.48452"
    },
    {
        "PPG": "0.54154",
        "ABP": "68.644",
        "ECG": "0.51548"
    },
    {
        "PPG": "0.56012",
        "ABP": "68.644",
        "ECG": "0.5"
    },
    {
        "PPG": "0.57478",
        "ABP": "68.449",
        "ECG": "0.52477"
    },
    {
        "PPG": "0.58749",
        "ABP": "68.253",
        "ECG": "0.51548"
    },
    {
        "PPG": "0.59726",
        "ABP": "68.057",
        "ECG": "0.54025"
    },
    {
        "PPG": "0.60411",
        "ABP": "67.666",
        "ECG": "0.52477"
    },
    {
        "PPG": "0.60899",
        "ABP": "67.275",
        "ECG": "0.54489"
    },
    {
        "PPG": "0.61193",
        "ABP": "66.884",
        "ECG": "0.5356"
    },
    {
        "PPG": "0.61193",
        "ABP": "66.493",
        "ECG": "0.55573"
    },
    {
        "PPG": "0.60997",
        "ABP": "65.906",
        "ECG": "0.54025"
    },
    {
        "PPG": "0.60802",
        "ABP": "65.515",
        "ECG": "0.56966"
    },
    {
        "PPG": "0.60606",
        "ABP": "64.928",
        "ECG": "0.56037"
    },
    {
        "PPG": "0.60313",
        "ABP": "64.537",
        "ECG": "0.59598"
    },
    {
        "PPG": "0.6002",
        "ABP": "64.146",
        "ECG": "0.59598"
    },
    {
        "PPG": "0.59629",
        "ABP": "63.95",
        "ECG": "0.64087"
    },
    {
        "PPG": "0.5914",
        "ABP": "63.755",
        "ECG": "0.6548"
    },
    {
        "PPG": "0.58651",
        "ABP": "63.755",
        "ECG": "0.70588"
    },
    {
        "PPG": "0.58065",
        "ABP": "63.755",
        "ECG": "0.71517"
    },
    {
        "PPG": "0.5738",
        "ABP": "64.146",
        "ECG": "0.75542"
    },
    {
        "PPG": "0.56794",
        "ABP": "64.537",
        "ECG": "0.74613"
    },
    {
        "PPG": "0.56109",
        "ABP": "65.906",
        "ECG": "0.75542"
    },
    {
        "PPG": "0.55425",
        "ABP": "68.449",
        "ECG": "0.73065"
    },
    {
        "PPG": "0.54839",
        "ABP": "72.751",
        "ECG": "0.71053"
    },
    {
        "PPG": "0.5435",
        "ABP": "79.009",
        "ECG": "0.67028"
    },
    {
        "PPG": "0.53861",
        "ABP": "86.832",
        "ECG": "0.64087"
    },
    {
        "PPG": "0.53372",
        "ABP": "95.437",
        "ECG": "0.60526"
    },
    {
        "PPG": "0.53079",
        "ABP": "103.46",
        "ECG": "0.5805"
    },
    {
        "PPG": "0.52981",
        "ABP": "109.71",
        "ECG": "0.58514"
    },
    {
        "PPG": "0.5259",
        "ABP": "113.62",
        "ECG": "0.54489"
    },
    {
        "PPG": "0.52004",
        "ABP": "115.78",
        "ECG": "0.56037"
    },
    {
        "PPG": "0.5132",
        "ABP": "115.78",
        "ECG": "0.5356"
    },
    {
        "PPG": "0.50635",
        "ABP": "114.6",
        "ECG": "0.54954"
    },
    {
        "PPG": "0.50049",
        "ABP": "112.26",
        "ECG": "0.5356"
    },
    {
        "PPG": "0.49462",
        "ABP": "108.93",
        "ECG": "0.56502"
    },
    {
        "PPG": "0.48974",
        "ABP": "104.82",
        "ECG": "0.56037"
    },
    {
        "PPG": "0.48583",
        "ABP": "100.13",
        "ECG": "0.60062"
    },
    {
        "PPG": "0.48192",
        "ABP": "95.241",
        "ECG": "0.58514"
    },
    {
        "PPG": "0.47801",
        "ABP": "90.352",
        "ECG": "0.60062"
    },
    {
        "PPG": "0.47312",
        "ABP": "85.463",
        "ECG": "0.57585"
    },
    {
        "PPG": "0.46823",
        "ABP": "81.16",
        "ECG": "0.56502"
    },
    {
        "PPG": "0.46334",
        "ABP": "77.64",
        "ECG": "0.54489"
    },
    {
        "PPG": "0.45748",
        "ABP": "75.098",
        "ECG": "0.56502"
    },
    {
        "PPG": "0.45161",
        "ABP": "73.338",
        "ECG": "0.52941"
    },
    {
        "PPG": "0.44673",
        "ABP": "72.36",
        "ECG": "0.54025"
    },
    {
        "PPG": "0.44086",
        "ABP": "71.969",
        "ECG": "0.52477"
    },
    {
        "PPG": "0.43597",
        "ABP": "72.164",
        "ECG": "0.52012"
    },
    {
        "PPG": "0.43011",
        "ABP": "72.36",
        "ECG": "0.5356"
    },
    {
        "PPG": "0.42424",
        "ABP": "72.751",
        "ECG": "0.51548"
    },
    {
        "PPG": "0.41935",
        "ABP": "73.142",
        "ECG": "0.52941"
    },
    {
        "PPG": "0.41544",
        "ABP": "73.533",
        "ECG": "0.51548"
    },
    {
        "PPG": "0.41153",
        "ABP": "73.533",
        "ECG": "0.52941"
    },
    {
        "PPG": "0.40958",
        "ABP": "73.533",
        "ECG": "0.51548"
    },
    {
        "PPG": "0.4086",
        "ABP": "73.338",
        "ECG": "0.52941"
    },
    {
        "PPG": "0.4086",
        "ABP": "72.751",
        "ECG": "0.51548"
    },
    {
        "PPG": "0.4086",
        "ABP": "72.164",
        "ECG": "0.5356"
    },
    {
        "PPG": "0.41153",
        "ABP": "71.773",
        "ECG": "0.52012"
    },
    {
        "PPG": "0.41544",
        "ABP": "70.991",
        "ECG": "0.56037"
    },
    {
        "PPG": "0.42229",
        "ABP": "70.404",
        "ECG": "0.60526"
    },
    {
        "PPG": "0.43304",
        "ABP": "69.622",
        "ECG": "0.69505"
    },
    {
        "PPG": "0.44673",
        "ABP": "69.035",
        "ECG": "0.50464"
    },
    {
        "PPG": "0.46432",
        "ABP": "68.449",
        "ECG": "0.28483"
    },
    {
        "PPG": "0.48387",
        "ABP": "68.057",
        "ECG": "0.22446"
    },
    {
        "PPG": "0.50538",
        "ABP": "67.862",
        "ECG": "0.33437"
    },
    {
        "PPG": "0.52786",
        "ABP": "67.471",
        "ECG": "0.45511"
    },
    {
        "PPG": "0.54839",
        "ABP": "67.275",
        "ECG": "0.54489"
    },
    {
        "PPG": "0.56696",
        "ABP": "67.08",
        "ECG": "0.56037"
    },
    {
        "PPG": "0.58749",
        "ABP": "66.884",
        "ECG": "0.58514"
    },
    {
        "PPG": "0.60704",
        "ABP": "66.688",
        "ECG": "0.5805"
    },
    {
        "PPG": "0.62463",
        "ABP": "66.493",
        "ECG": "0.60062"
    },
    {
        "PPG": "0.64125",
        "ABP": "66.102",
        "ECG": "0.60526"
    },
    {
        "PPG": "0.65494",
        "ABP": "65.906",
        "ECG": "0.60062"
    },
    {
        "PPG": "0.66569",
        "ABP": "65.515",
        "ECG": "0.60991"
    },
    {
        "PPG": "0.67351",
        "ABP": "65.124",
        "ECG": "0.60526"
    },
    {
        "PPG": "0.67937",
        "ABP": "64.733",
        "ECG": "0.62074"
    },
    {
        "PPG": "0.68133",
        "ABP": "64.342",
        "ECG": "0.60991"
    },
    {
        "PPG": "0.68231",
        "ABP": "63.755",
        "ECG": "0.63467"
    },
    {
        "PPG": "0.68231",
        "ABP": "63.364",
        "ECG": "0.62074"
    },
    {
        "PPG": "0.68035",
        "ABP": "62.777",
        "ECG": "0.64551"
    },
    {
        "PPG": "0.67644",
        "ABP": "62.19",
        "ECG": "0.63467"
    },
    {
        "PPG": "0.67253",
        "ABP": "61.604",
        "ECG": "0.66563"
    },
    {
        "PPG": "0.66764",
        "ABP": "61.213",
        "ECG": "0.67492"
    },
    {
        "PPG": "0.6608",
        "ABP": "60.821",
        "ECG": "0.70588"
    },
    {
        "PPG": "0.65396",
        "ABP": "60.43",
        "ECG": "0.72601"
    },
    {
        "PPG": "0.64614",
        "ABP": "60.235",
        "ECG": "0.7709"
    },
    {
        "PPG": "0.63832",
        "ABP": "60.235",
        "ECG": "0.79102"
    },
    {
        "PPG": "0.62952",
        "ABP": "60.43",
        "ECG": "0.83127"
    },
    {
        "PPG": "0.6217",
        "ABP": "60.821",
        "ECG": "0.82508"
    },
    {
        "PPG": "0.61388",
        "ABP": "61.604",
        "ECG": "0.8452"
    },
    {
        "PPG": "0.60411",
        "ABP": "63.168",
        "ECG": "0.81115"
    },
    {
        "PPG": "0.59531",
        "ABP": "66.297",
        "ECG": "0.80495"
    },
    {
        "PPG": "0.58651",
        "ABP": "71.186",
        "ECG": "0.75542"
    },
    {
        "PPG": "0.57674",
        "ABP": "78.031",
        "ECG": "0.73994"
    },
    {
        "PPG": "0.56696",
        "ABP": "86.05",
        "ECG": "0.69505"
    },
    {
        "PPG": "0.55914",
        "ABP": "94.263",
        "ECG": "0.67492"
    },
    {
        "PPG": "0.55034",
        "ABP": "101.5",
        "ECG": "0.64551"
    },
    {
        "PPG": "0.5435",
        "ABP": "106.98",
        "ECG": "0.63467"
    },
    {
        "PPG": "0.53666",
        "ABP": "110.5",
        "ECG": "0.62074"
    },
    {
        "PPG": "0.52786",
        "ABP": "111.86",
        "ECG": "0.60991"
    },
    {
        "PPG": "0.52004",
        "ABP": "111.86",
        "ECG": "0.62074"
    },
    {
        "PPG": "0.51124",
        "ABP": "110.1",
        "ECG": "0.60526"
    },
    {
        "PPG": "0.50244",
        "ABP": "107.37",
        "ECG": "0.62074"
    },
    {
        "PPG": "0.49365",
        "ABP": "103.65",
        "ECG": "0.60991"
    },
    {
        "PPG": "0.4868",
        "ABP": "99.348",
        "ECG": "0.64551"
    },
    {
        "PPG": "0.48192",
        "ABP": "94.459",
        "ECG": "0.65015"
    },
    {
        "PPG": "0.47605",
        "ABP": "89.57",
        "ECG": "0.66099"
    },
    {
        "PPG": "0.46921",
        "ABP": "84.485",
        "ECG": "0.63467"
    },
    {
        "PPG": "0.46237",
        "ABP": "79.791",
        "ECG": "0.64087"
    },
    {
        "PPG": "0.45357",
        "ABP": "75.88",
        "ECG": "0.58978"
    },
    {
        "PPG": "0.44477",
        "ABP": "72.751",
        "ECG": "0.60062"
    },
    {
        "PPG": "0.43597",
        "ABP": "70.404",
        "ECG": "0.57585"
    },
    {
        "PPG": "0.42717",
        "ABP": "69.231",
        "ECG": "0.56966"
    },
    {
        "PPG": "0.41935",
        "ABP": "68.84",
        "ECG": "0.55573"
    },
    {
        "PPG": "0.41153",
        "ABP": "69.035",
        "ECG": "0.56502"
    },
    {
        "PPG": "0.40371",
        "ABP": "69.622",
        "ECG": "0.54025"
    },
    {
        "PPG": "0.39687",
        "ABP": "70.404",
        "ECG": "0.55573"
    },
    {
        "PPG": "0.39003",
        "ABP": "71.186",
        "ECG": "0.54025"
    },
    {
        "PPG": "0.38319",
        "ABP": "71.969",
        "ECG": "0.55573"
    },
    {
        "PPG": "0.37537",
        "ABP": "72.36",
        "ECG": "0.54025"
    },
    {
        "PPG": "0.3695",
        "ABP": "72.555",
        "ECG": "0.54489"
    },
    {
        "PPG": "0.36364",
        "ABP": "72.555",
        "ECG": "0.52941"
    },
    {
        "PPG": "0.35875",
        "ABP": "72.164",
        "ECG": "0.54025"
    },
    {
        "PPG": "0.35582",
        "ABP": "71.578",
        "ECG": "0.52941"
    },
    {
        "PPG": "0.35484",
        "ABP": "70.991",
        "ECG": "0.52477"
    },
    {
        "PPG": "0.35777",
        "ABP": "70.209",
        "ECG": "0.54489"
    },
    {
        "PPG": "0.36266",
        "ABP": "69.426",
        "ECG": "0.56966"
    },
    {
        "PPG": "0.37048",
        "ABP": "68.644",
        "ECG": "0.63003"
    },
    {
        "PPG": "0.38123",
        "ABP": "68.057",
        "ECG": "0.66563"
    },
    {
        "PPG": "0.39394",
        "ABP": "67.471",
        "ECG": "0.41022"
    },
    {
        "PPG": "0.4086",
        "ABP": "66.884",
        "ECG": "0.22446"
    },
    {
        "PPG": "0.42522",
        "ABP": "66.493",
        "ECG": "0.21362"
    },
    {
        "PPG": "0.44575",
        "ABP": "66.297",
        "ECG": "0.33901"
    },
    {
        "PPG": "0.46628",
        "ABP": "66.102",
        "ECG": "0.48452"
    },
    {
        "PPG": "0.48778",
        "ABP": "65.906",
        "ECG": "0.5356"
    },
    {
        "PPG": "0.50929",
        "ABP": "65.906",
        "ECG": "0.56502"
    },
    {
        "PPG": "0.52981",
        "ABP": "65.906",
        "ECG": "0.56502"
    },
    {
        "PPG": "0.54839",
        "ABP": "65.711",
        "ECG": "0.58514"
    },
    {
        "PPG": "0.56403",
        "ABP": "65.711",
        "ECG": "0.57585"
    },
    {
        "PPG": "0.57869",
        "ABP": "65.515",
        "ECG": "0.60062"
    },
    {
        "PPG": "0.58944",
        "ABP": "65.124",
        "ECG": "0.58978"
    },
    {
        "PPG": "0.59726",
        "ABP": "64.928",
        "ECG": "0.60991"
    },
    {
        "PPG": "0.60313",
        "ABP": "64.537",
        "ECG": "0.59598"
    },
    {
        "PPG": "0.60704",
        "ABP": "64.342",
        "ECG": "0.61455"
    },
    {
        "PPG": "0.61095",
        "ABP": "63.755",
        "ECG": "0.60062"
    },
    {
        "PPG": "0.61193",
        "ABP": "63.364",
        "ECG": "0.62074"
    },
    {
        "PPG": "0.61193",
        "ABP": "62.973",
        "ECG": "0.60991"
    },
    {
        "PPG": "0.61095",
        "ABP": "62.386",
        "ECG": "0.63467"
    },
    {
        "PPG": "0.60899",
        "ABP": "61.799",
        "ECG": "0.63003"
    },
    {
        "PPG": "0.60508",
        "ABP": "61.213",
        "ECG": "0.6548"
    },
    {
        "PPG": "0.59922",
        "ABP": "60.626",
        "ECG": "0.66099"
    },
    {
        "PPG": "0.59335",
        "ABP": "60.235",
        "ECG": "0.69505"
    },
    {
        "PPG": "0.58749",
        "ABP": "60.039",
        "ECG": "0.71981"
    },
    {
        "PPG": "0.58162",
        "ABP": "59.844",
        "ECG": "0.75077"
    },
    {
        "PPG": "0.57478",
        "ABP": "59.844",
        "ECG": "0.78019"
    },
    {
        "PPG": "0.56794",
        "ABP": "60.039",
        "ECG": "0.80031"
    },
    {
        "PPG": "0.56109",
        "ABP": "60.626",
        "ECG": "0.82043"
    },
    {
        "PPG": "0.55327",
        "ABP": "61.604",
        "ECG": "0.80495"
    },
    {
        "PPG": "0.54545",
        "ABP": "63.364",
        "ECG": "0.81115"
    },
    {
        "PPG": "0.53666",
        "ABP": "66.688",
        "ECG": "0.76625"
    },
    {
        "PPG": "0.52884",
        "ABP": "71.773",
        "ECG": "0.73994"
    },
    {
        "PPG": "0.52102",
        "ABP": "78.618",
        "ECG": "0.69969"
    },
    {
        "PPG": "0.51417",
        "ABP": "86.441",
        "ECG": "0.68111"
    },
    {
        "PPG": "0.50733",
        "ABP": "94.263",
        "ECG": "0.63467"
    },
    {
        "PPG": "0.50049",
        "ABP": "101.11",
        "ECG": "0.64087"
    },
    {
        "PPG": "0.49365",
        "ABP": "106.19",
        "ECG": "0.60062"
    },
    {
        "PPG": "0.48778",
        "ABP": "109.52",
        "ECG": "0.60991"
    },
    {
        "PPG": "0.48289",
        "ABP": "110.69",
        "ECG": "0.58978"
    },
    {
        "PPG": "0.47801",
        "ABP": "110.5",
        "ECG": "0.60062"
    },
    {
        "PPG": "0.47116",
        "ABP": "108.93",
        "ECG": "0.5805"
    },
    {
        "PPG": "0.4653",
        "ABP": "106.19",
        "ECG": "0.60062"
    },
    {
        "PPG": "0.45846",
        "ABP": "102.48",
        "ECG": "0.60526"
    },
    {
        "PPG": "0.45064",
        "ABP": "97.979",
        "ECG": "0.62539"
    },
    {
        "PPG": "0.44379",
        "ABP": "93.286",
        "ECG": "0.61455"
    },
    {
        "PPG": "0.43793",
        "ABP": "88.201",
        "ECG": "0.62074"
    },
    {
        "PPG": "0.43109",
        "ABP": "83.116",
        "ECG": "0.60526"
    },
    {
        "PPG": "0.42522",
        "ABP": "78.618",
        "ECG": "0.5805"
    },
    {
        "PPG": "0.42033",
        "ABP": "74.707",
        "ECG": "0.56037"
    },
    {
        "PPG": "0.41447",
        "ABP": "71.773",
        "ECG": "0.56502"
    },
    {
        "PPG": "0.4086",
        "ABP": "69.622",
        "ECG": "0.54489"
    },
    {
        "PPG": "0.40567",
        "ABP": "68.644",
        "ECG": "0.52941"
    },
    {
        "PPG": "0.40176",
        "ABP": "68.449",
        "ECG": "0.54025"
    },
    {
        "PPG": "0.39687",
        "ABP": "68.84",
        "ECG": "0.51548"
    },
    {
        "PPG": "0.39101",
        "ABP": "69.426",
        "ECG": "0.52477"
    },
    {
        "PPG": "0.38416",
        "ABP": "70.404",
        "ECG": "0.50929"
    },
    {
        "PPG": "0.37732",
        "ABP": "71.186",
        "ECG": "0.51548"
    },
    {
        "PPG": "0.36852",
        "ABP": "71.773",
        "ECG": "0.5"
    },
    {
        "PPG": "0.3607",
        "ABP": "72.164",
        "ECG": "0.51548"
    },
    {
        "PPG": "0.35484",
        "ABP": "72.36",
        "ECG": "0.49536"
    },
    {
        "PPG": "0.34995",
        "ABP": "72.164",
        "ECG": "0.50464"
    },
    {
        "PPG": "0.34604",
        "ABP": "71.773",
        "ECG": "0.49071"
    },
    {
        "PPG": "0.34409",
        "ABP": "71.186",
        "ECG": "0.50464"
    },
    {
        "PPG": "0.34409",
        "ABP": "70.404",
        "ECG": "0.49536"
    },
    {
        "PPG": "0.34604",
        "ABP": "69.622",
        "ECG": "0.52012"
    },
    {
        "PPG": "0.34995",
        "ABP": "69.035",
        "ECG": "0.54489"
    },
    {
        "PPG": "0.35777",
        "ABP": "68.253",
        "ECG": "0.64551"
    },
    {
        "PPG": "0.36852",
        "ABP": "67.666",
        "ECG": "0.54489"
    },
    {
        "PPG": "0.38416",
        "ABP": "67.275",
        "ECG": "0.28019"
    },
    {
        "PPG": "0.40078",
        "ABP": "67.08",
        "ECG": "0.16409"
    },
    {
        "PPG": "0.42033",
        "ABP": "66.688",
        "ECG": "0.20898"
    },
    {
        "PPG": "0.44184",
        "ABP": "66.688",
        "ECG": "0.3452"
    },
    {
        "PPG": "0.46334",
        "ABP": "66.688",
        "ECG": "0.4644"
    },
    {
        "PPG": "0.48583",
        "ABP": "66.688",
        "ECG": "0.49536"
    },
    {
        "PPG": "0.50733",
        "ABP": "66.688",
        "ECG": "0.51548"
    },
    {
        "PPG": "0.5259",
        "ABP": "66.884",
        "ECG": "0.52477"
    },
    {
        "PPG": "0.54154",
        "ABP": "66.884",
        "ECG": "0.51548"
    },
    {
        "PPG": "0.55718",
        "ABP": "66.884",
        "ECG": "0.54025"
    },
    {
        "PPG": "0.56989",
        "ABP": "66.688",
        "ECG": "0.52477"
    },
    {
        "PPG": "0.58162",
        "ABP": "66.688",
        "ECG": "0.54025"
    },
    {
        "PPG": "0.59042",
        "ABP": "66.297",
        "ECG": "0.52012"
    },
    {
        "PPG": "0.59629",
        "ABP": "66.102",
        "ECG": "0.54025"
    },
    {
        "PPG": "0.60117",
        "ABP": "65.711",
        "ECG": "0.52477"
    },
    {
        "PPG": "0.60411",
        "ABP": "65.319",
        "ECG": "0.54025"
    },
    {
        "PPG": "0.60411",
        "ABP": "64.928",
        "ECG": "0.5356"
    },
    {
        "PPG": "0.60411",
        "ABP": "64.537",
        "ECG": "0.54954"
    },
    {
        "PPG": "0.60215",
        "ABP": "63.95",
        "ECG": "0.54025"
    },
    {
        "PPG": "0.59922",
        "ABP": "63.364",
        "ECG": "0.56966"
    },
    {
        "PPG": "0.59629",
        "ABP": "62.973",
        "ECG": "0.56502"
    },
    {
        "PPG": "0.59238",
        "ABP": "62.582",
        "ECG": "0.60526"
    },
    {
        "PPG": "0.58651",
        "ABP": "62.19",
        "ECG": "0.62074"
    },
    {
        "PPG": "0.58065",
        "ABP": "62.19",
        "ECG": "0.66563"
    },
    {
        "PPG": "0.57478",
        "ABP": "62.19",
        "ECG": "0.68111"
    },
    {
        "PPG": "0.56891",
        "ABP": "62.386",
        "ECG": "0.72601"
    },
    {
        "PPG": "0.56207",
        "ABP": "62.582",
        "ECG": "0.73065"
    },
    {
        "PPG": "0.55523",
        "ABP": "63.364",
        "ECG": "0.74613"
    },
    {
        "PPG": "0.54936",
        "ABP": "64.733",
        "ECG": "0.72601"
    },
    {
        "PPG": "0.54448",
        "ABP": "67.471",
        "ECG": "0.71517"
    },
    {
        "PPG": "0.53763",
        "ABP": "71.773",
        "ECG": "0.68111"
    },
    {
        "PPG": "0.53275",
        "ABP": "77.836",
        "ECG": "0.65015"
    },
    {
        "PPG": "0.52688",
        "ABP": "85.658",
        "ECG": "0.60991"
    },
    {
        "PPG": "0.52199",
        "ABP": "93.677",
        "ECG": "0.58514"
    },
    {
        "PPG": "0.51613",
        "ABP": "101.5",
        "ECG": "0.56037"
    },
    {
        "PPG": "0.50929",
        "ABP": "107.56",
        "ECG": "0.54025"
    },
    {
        "PPG": "0.50342",
        "ABP": "111.86",
        "ECG": "0.52941"
    },
    {
        "PPG": "0.49658",
        "ABP": "113.82",
        "ECG": "0.51548"
    },
    {
        "PPG": "0.48974",
        "ABP": "114.21",
        "ECG": "0.52941"
    },
    {
        "PPG": "0.48289",
        "ABP": "113.23",
        "ECG": "0.51548"
    },
    {
        "PPG": "0.47605",
        "ABP": "110.89",
        "ECG": "0.52941"
    },
    {
        "PPG": "0.46921",
        "ABP": "107.76",
        "ECG": "0.52012"
    },
    {
        "PPG": "0.46334",
        "ABP": "103.65",
        "ECG": "0.56037"
    },
    {
        "PPG": "0.4565",
        "ABP": "99.153",
        "ECG": "0.54954"
    },
    {
        "PPG": "0.45161",
        "ABP": "94.263",
        "ECG": "0.56502"
    },
    {
        "PPG": "0.4477",
        "ABP": "89.179",
        "ECG": "0.54489"
    },
    {
        "PPG": "0.44379",
        "ABP": "84.485",
        "ECG": "0.54954"
    },
    {
        "PPG": "0.43988",
        "ABP": "80.378",
        "ECG": "0.50464"
    },
    {
        "PPG": "0.43597",
        "ABP": "77.249",
        "ECG": "0.52012"
    },
    {
        "PPG": "0.43011",
        "ABP": "74.902",
        "ECG": "0.49071"
    },
    {
        "PPG": "0.42424",
        "ABP": "73.729",
        "ECG": "0.48452"
    },
    {
        "PPG": "0.41935",
        "ABP": "73.338",
        "ECG": "0.4644"
    },
    {
        "PPG": "0.41544",
        "ABP": "73.533",
        "ECG": "0.47523"
    },
    {
        "PPG": "0.41056",
        "ABP": "74.12",
        "ECG": "0.4644"
    },
    {
        "PPG": "0.40567",
        "ABP": "74.902",
        "ECG": "0.45511"
    },
    {
        "PPG": "0.3998",
        "ABP": "75.489",
        "ECG": "0.47059"
    },
    {
        "PPG": "0.39492",
        "ABP": "76.271",
        "ECG": "0.45046"
    },
    {
        "PPG": "0.39101",
        "ABP": "76.662",
        "ECG": "0.4644"
    },
    {
        "PPG": "0.38612",
        "ABP": "76.858",
        "ECG": "0.44427"
    },
    {
        "PPG": "0.38221",
        "ABP": "76.662",
        "ECG": "0.4644"
    },
    {
        "PPG": "0.3783",
        "ABP": "76.467",
        "ECG": "0.45046"
    },
    {
        "PPG": "0.37439",
        "ABP": "75.88",
        "ECG": "0.47059"
    },
    {
        "PPG": "0.37341",
        "ABP": "75.293",
        "ECG": "0.45046"
    },
    {
        "PPG": "0.37537",
        "ABP": "74.511",
        "ECG": "0.47988"
    },
    {
        "PPG": "0.38025",
        "ABP": "73.729",
        "ECG": "0.47523"
    },
    {
        "PPG": "0.39003",
        "ABP": "73.142",
        "ECG": "0.58978"
    },
    {
        "PPG": "0.40371",
        "ABP": "72.555",
        "ECG": "0.63003"
    },
    {
        "PPG": "0.41935",
        "ABP": "71.969",
        "ECG": "0.39009"
    },
    {
        "PPG": "0.43793",
        "ABP": "71.578",
        "ECG": "0.20898"
    },
    {
        "PPG": "0.45552",
        "ABP": "71.186",
        "ECG": "0.19969"
    },
    {
        "PPG": "0.47214",
        "ABP": "70.991",
        "ECG": "0.33437"
    },
    {
        "PPG": "0.49267",
        "ABP": "70.795",
        "ECG": "0.45975"
    },
    {
        "PPG": "0.51417",
        "ABP": "70.6",
        "ECG": "0.49071"
    },
    {
        "PPG": "0.53666",
        "ABP": "70.6",
        "ECG": "0.52012"
    },
    {
        "PPG": "0.55914",
        "ABP": "70.404",
        "ECG": "0.52012"
    },
    {
        "PPG": "0.57967",
        "ABP": "70.209",
        "ECG": "0.54025"
    },
    {
        "PPG": "0.59922",
        "ABP": "70.013",
        "ECG": "0.54489"
    },
    {
        "PPG": "0.61681",
        "ABP": "69.622",
        "ECG": "0.56037"
    },
    {
        "PPG": "0.63148",
        "ABP": "69.426",
        "ECG": "0.55573"
    },
    {
        "PPG": "0.64418",
        "ABP": "69.035",
        "ECG": "0.57585"
    },
    {
        "PPG": "0.65298",
        "ABP": "68.449",
        "ECG": "0.56502"
    },
    {
        "PPG": "0.65885",
        "ABP": "67.666",
        "ECG": "0.58514"
    },
    {
        "PPG": "0.66178",
        "ABP": "67.08",
        "ECG": "0.58978"
    },
    {
        "PPG": "0.66373",
        "ABP": "66.102",
        "ECG": "0.57585"
    },
    {
        "PPG": "0.66373",
        "ABP": "65.319",
        "ECG": "0.60062"
    },
    {
        "PPG": "0.66276",
        "ABP": "64.342",
        "ECG": "0.58978"
    },
    {
        "PPG": "0.66178",
        "ABP": "63.364",
        "ECG": "0.61455"
    },
    {
        "PPG": "0.65298",
        "ABP": "62.582",
        "ECG": "0.60991"
    },
    {
        "PPG": "0.6393",
        "ABP": "61.995",
        "ECG": "0.64551"
    },
    {
        "PPG": "0.63148",
        "ABP": "61.408",
        "ECG": "0.66563"
    },
    {
        "PPG": "0.62366",
        "ABP": "61.017",
        "ECG": "0.70588"
    },
    {
        "PPG": "0.61681",
        "ABP": "61.017",
        "ECG": "0.72601"
    },
    {
        "PPG": "0.60997",
        "ABP": "61.017",
        "ECG": "0.76625"
    },
    {
        "PPG": "0.60411",
        "ABP": "61.213",
        "ECG": "0.77554"
    },
    {
        "PPG": "0.59824",
        "ABP": "61.799",
        "ECG": "0.80031"
    },
    {
        "PPG": "0.59433",
        "ABP": "63.168",
        "ECG": "0.78019"
    },
    {
        "PPG": "0.59042",
        "ABP": "65.515",
        "ECG": "0.77554"
    },
    {
        "PPG": "0.58553",
        "ABP": "69.622",
        "ECG": "0.73529"
    },
    {
        "PPG": "0.57967",
        "ABP": "75.685",
        "ECG": "0.71517"
    },
    {
        "PPG": "0.57478",
        "ABP": "83.507",
        "ECG": "0.67028"
    },
    {
        "PPG": "0.56891",
        "ABP": "92.112",
        "ECG": "0.6548"
    },
    {
        "PPG": "0.56305",
        "ABP": "100.33",
        "ECG": "0.61455"
    },
    {
        "PPG": "0.55718",
        "ABP": "106.98",
        "ECG": "0.60526"
    },
    {
        "PPG": "0.55132",
        "ABP": "111.67",
        "ECG": "0.5805"
    },
    {
        "PPG": "0.54448",
        "ABP": "114.02",
        "ECG": "0.58978"
    },
    {
        "PPG": "0.53763",
        "ABP": "114.41",
        "ECG": "0.56966"
    },
    {
        "PPG": "0.53177",
        "ABP": "113.23",
        "ECG": "0.56502"
    },
    {
        "PPG": "0.5259",
        "ABP": "110.69",
        "ECG": "0.58514"
    },
    {
        "PPG": "0.51906",
        "ABP": "107.37",
        "ECG": "0.56502"
    },
    {
        "PPG": "0.5132",
        "ABP": "103.06",
        "ECG": "0.58978"
    },
    {
        "PPG": "0.50733",
        "ABP": "98.37",
        "ECG": "0.61455"
    },
    {
        "PPG": "0.50049",
        "ABP": "93.286",
        "ECG": "0.62539"
    },
    {
        "PPG": "0.49462",
        "ABP": "88.201",
        "ECG": "0.60991"
    },
    {
        "PPG": "0.48778",
        "ABP": "83.507",
        "ECG": "0.61455"
    },
    {
        "PPG": "0.48192",
        "ABP": "79.009",
        "ECG": "0.57585"
    },
    {
        "PPG": "0.47605",
        "ABP": "75.489",
        "ECG": "0.56502"
    },
    {
        "PPG": "0.47019",
        "ABP": "72.751",
        "ECG": "0.56037"
    },
    {
        "PPG": "0.46432",
        "ABP": "70.795",
        "ECG": "0.56502"
    },
    {
        "PPG": "0.45846",
        "ABP": "70.013",
        "ECG": "0.52941"
    },
    {
        "PPG": "0.45357",
        "ABP": "69.818",
        "ECG": "0.54025"
    },
    {
        "PPG": "0.4477",
        "ABP": "70.209",
        "ECG": "0.52477"
    },
    {
        "PPG": "0.44184",
        "ABP": "70.795",
        "ECG": "0.54025"
    },
    {
        "PPG": "0.43304",
        "ABP": "71.578",
        "ECG": "0.52012"
    },
    {
        "PPG": "0.42522",
        "ABP": "72.36",
        "ECG": "0.5356"
    },
    {
        "PPG": "0.41642",
        "ABP": "72.947",
        "ECG": "0.51548"
    },
    {
        "PPG": "0.40958",
        "ABP": "73.338",
        "ECG": "0.52941"
    },
    {
        "PPG": "0.40274",
        "ABP": "73.533",
        "ECG": "0.51548"
    },
    {
        "PPG": "0.39785",
        "ABP": "73.338",
        "ECG": "0.52941"
    },
    {
        "PPG": "0.39394",
        "ABP": "72.947",
        "ECG": "0.51548"
    },
    {
        "PPG": "0.39198",
        "ABP": "72.36",
        "ECG": "0.52477"
    },
    {
        "PPG": "0.39296",
        "ABP": "71.578",
        "ECG": "0.51548"
    },
    {
        "PPG": "0.39589",
        "ABP": "70.795",
        "ECG": "0.54489"
    },
    {
        "PPG": "0.40176",
        "ABP": "70.013",
        "ECG": "0.57585"
    },
    {
        "PPG": "0.41056",
        "ABP": "69.231",
        "ECG": "0.66563"
    },
    {
        "PPG": "0.42131",
        "ABP": "68.644",
        "ECG": "0.67028"
    },
    {
        "PPG": "0.435",
        "ABP": "68.057",
        "ECG": "0.31889"
    },
    {
        "PPG": "0.45064",
        "ABP": "67.666",
        "ECG": "0.21362"
    },
    {
        "PPG": "0.46823",
        "ABP": "67.275",
        "ECG": "0.20433"
    },
    {
        "PPG": "0.48583",
        "ABP": "66.884",
        "ECG": "0.39938"
    },
    {
        "PPG": "0.50538",
        "ABP": "66.688",
        "ECG": "0.5"
    },
    {
        "PPG": "0.52395",
        "ABP": "66.688",
        "ECG": "0.55573"
    },
    {
        "PPG": "0.54252",
        "ABP": "66.493",
        "ECG": "0.56037"
    },
    {
        "PPG": "0.56012",
        "ABP": "66.493",
        "ECG": "0.5805"
    },
    {
        "PPG": "0.57576",
        "ABP": "66.297",
        "ECG": "0.56966"
    },
    {
        "PPG": "0.58651",
        "ABP": "66.102",
        "ECG": "0.59598"
    },
    {
        "PPG": "0.59531",
        "ABP": "65.906",
        "ECG": "0.58514"
    },
    {
        "PPG": "0.60215",
        "ABP": "65.711",
        "ECG": "0.60062"
    },
    {
        "PPG": "0.60704",
        "ABP": "65.515",
        "ECG": "0.58514"
    },
    {
        "PPG": "0.60997",
        "ABP": "65.124",
        "ECG": "0.60526"
    },
    {
        "PPG": "0.61095",
        "ABP": "64.537",
        "ECG": "0.58978"
    },
    {
        "PPG": "0.60997",
        "ABP": "64.146",
        "ECG": "0.60991"
    },
    {
        "PPG": "0.60704",
        "ABP": "63.755",
        "ECG": "0.60062"
    },
    {
        "PPG": "0.60411",
        "ABP": "63.168",
        "ECG": "0.61455"
    },
    {
        "PPG": "0.60117",
        "ABP": "62.582",
        "ECG": "0.60991"
    },
    {
        "PPG": "0.59726",
        "ABP": "61.995",
        "ECG": "0.63467"
    },
    {
        "PPG": "0.59433",
        "ABP": "61.408",
        "ECG": "0.64087"
    },
    {
        "PPG": "0.58944",
        "ABP": "61.017",
        "ECG": "0.67028"
    },
    {
        "PPG": "0.58456",
        "ABP": "60.626",
        "ECG": "0.68576"
    },
    {
        "PPG": "0.57967",
        "ABP": "60.235",
        "ECG": "0.72601"
    },
    {
        "PPG": "0.57283",
        "ABP": "60.235",
        "ECG": "0.75077"
    },
    {
        "PPG": "0.56598",
        "ABP": "60.235",
        "ECG": "0.78019"
    },
    {
        "PPG": "0.55816",
        "ABP": "60.43",
        "ECG": "0.80031"
    },
    {
        "PPG": "0.55034",
        "ABP": "61.213",
        "ECG": "0.80495"
    },
    {
        "PPG": "0.54252",
        "ABP": "62.386",
        "ECG": "0.81115"
    },
    {
        "PPG": "0.53568",
        "ABP": "64.733",
        "ECG": "0.77554"
    },
    {
        "PPG": "0.52981",
        "ABP": "68.84",
        "ECG": "0.75542"
    },
    {
        "PPG": "0.52395",
        "ABP": "74.707",
        "ECG": "0.71053"
    },
    {
        "PPG": "0.51711",
        "ABP": "82.138",
        "ECG": "0.6904"
    },
    {
        "PPG": "0.51124",
        "ABP": "90.157",
        "ECG": "0.64551"
    },
    {
        "PPG": "0.50635",
        "ABP": "97.784",
        "ECG": "0.63467"
    },
    {
        "PPG": "0.50147",
        "ABP": "104.04",
        "ECG": "0.60526"
    },
    {
        "PPG": "0.4956",
        "ABP": "108.34",
        "ECG": "0.60991"
    },
    {
        "PPG": "0.48974",
        "ABP": "110.69",
        "ECG": "0.5805"
    },
    {
        "PPG": "0.48387",
        "ABP": "111.28",
        "ECG": "0.58978"
    },
    {
        "PPG": "0.47703",
        "ABP": "110.5",
        "ECG": "0.56502"
    },
    {
        "PPG": "0.47116",
        "ABP": "108.34",
        "ECG": "0.58514"
    },
    {
        "PPG": "0.46432",
        "ABP": "105.22",
        "ECG": "0.57585"
    },
    {
        "PPG": "0.45846",
        "ABP": "101.11",
        "ECG": "0.60991"
    },
    {
        "PPG": "0.45259",
        "ABP": "96.61",
        "ECG": "0.60991"
    },
    {
        "PPG": "0.44673",
        "ABP": "91.525",
        "ECG": "0.62074"
    },
    {
        "PPG": "0.44086",
        "ABP": "86.441",
        "ECG": "0.58978"
    },
    {
        "PPG": "0.43597",
        "ABP": "81.356",
        "ECG": "0.58978"
    },
    {
        "PPG": "0.43206",
        "ABP": "77.054",
        "ECG": "0.55573"
    },
    {
        "PPG": "0.4262",
        "ABP": "73.338",
        "ECG": "0.54489"
    },
    {
        "PPG": "0.42131",
        "ABP": "70.6",
        "ECG": "0.56037"
    },
    {
        "PPG": "0.41544",
        "ABP": "69.035",
        "ECG": "0.5356"
    },
    {
        "PPG": "0.41056",
        "ABP": "68.449",
        "ECG": "0.54025"
    },
    {
        "PPG": "0.40469",
        "ABP": "68.449",
        "ECG": "0.51548"
    },
    {
        "PPG": "0.39785",
        "ABP": "69.035",
        "ECG": "0.52477"
    },
    {
        "PPG": "0.39003",
        "ABP": "69.818",
        "ECG": "0.50464"
    },
    {
        "PPG": "0.38319",
        "ABP": "70.6",
        "ECG": "0.52012"
    },
    {
        "PPG": "0.37537",
        "ABP": "71.382",
        "ECG": "0.50464"
    },
    {
        "PPG": "0.36755",
        "ABP": "72.164",
        "ECG": "0.51548"
    },
    {
        "PPG": "0.35973",
        "ABP": "72.36",
        "ECG": "0.50464"
    },
    {
        "PPG": "0.35484",
        "ABP": "72.36",
        "ECG": "0.51548"
    },
    {
        "PPG": "0.35191",
        "ABP": "72.164",
        "ECG": "0.5"
    },
    {
        "PPG": "0.34995",
        "ABP": "71.773",
        "ECG": "0.51548"
    },
    {
        "PPG": "0.34897",
        "ABP": "71.186",
        "ECG": "0.5"
    },
    {
        "PPG": "0.34995",
        "ABP": "70.404",
        "ECG": "0.52477"
    },
    {
        "PPG": "0.35288",
        "ABP": "69.622",
        "ECG": "0.52012"
    },
    {
        "PPG": "0.35875",
        "ABP": "68.84",
        "ECG": "0.60062"
    },
    {
        "PPG": "0.36755",
        "ABP": "68.057",
        "ECG": "0.64551"
    },
    {
        "PPG": "0.37928",
        "ABP": "67.471",
        "ECG": "0.4644"
    },
    {
        "PPG": "0.39492",
        "ABP": "67.08",
        "ECG": "0.21981"
    },
    {
        "PPG": "0.41056",
        "ABP": "66.688",
        "ECG": "0.18885"
    },
    {
        "PPG": "0.42913",
        "ABP": "66.297",
        "ECG": "0.28019"
    },
    {
        "PPG": "0.44673",
        "ABP": "66.102",
        "ECG": "0.43963"
    },
    {
        "PPG": "0.46237",
        "ABP": "65.906",
        "ECG": "0.50929"
    },
    {
        "PPG": "0.48094",
        "ABP": "65.906",
        "ECG": "0.54954"
    },
    {
        "PPG": "0.49951",
        "ABP": "65.906",
        "ECG": "0.56037"
    },
    {
        "PPG": "0.51613",
        "ABP": "65.906",
        "ECG": "0.55573"
    },
    {
        "PPG": "0.53079",
        "ABP": "65.711",
        "ECG": "0.57585"
    },
    {
        "PPG": "0.54448",
        "ABP": "65.515",
        "ECG": "0.56502"
    },
    {
        "PPG": "0.55523",
        "ABP": "65.319",
        "ECG": "0.58978"
    },
    {
        "PPG": "0.565",
        "ABP": "65.124",
        "ECG": "0.5805"
    },
    {
        "PPG": "0.57283",
        "ABP": "64.733",
        "ECG": "0.58978"
    },
    {
        "PPG": "0.57869",
        "ABP": "64.342",
        "ECG": "0.58514"
    },
    {
        "PPG": "0.5826",
        "ABP": "63.95",
        "ECG": "0.60062"
    },
    {
        "PPG": "0.58456",
        "ABP": "63.364",
        "ECG": "0.58978"
    },
    {
        "PPG": "0.58553",
        "ABP": "62.973",
        "ECG": "0.60526"
    },
    {
        "PPG": "0.58456",
        "ABP": "62.386",
        "ECG": "0.59598"
    },
    {
        "PPG": "0.58358",
        "ABP": "61.799",
        "ECG": "0.62539"
    },
    {
        "PPG": "0.58162",
        "ABP": "61.213",
        "ECG": "0.61455"
    },
    {
        "PPG": "0.57967",
        "ABP": "60.626",
        "ECG": "0.64551"
    },
    {
        "PPG": "0.57576",
        "ABP": "60.235",
        "ECG": "0.6548"
    },
    {
        "PPG": "0.57185",
        "ABP": "60.039",
        "ECG": "0.69969"
    },
    {
        "PPG": "0.56598",
        "ABP": "59.844",
        "ECG": "0.71517"
    },
    {
        "PPG": "0.55914",
        "ABP": "59.844",
        "ECG": "0.76006"
    },
    {
        "PPG": "0.55132",
        "ABP": "60.039",
        "ECG": "0.76625"
    },
    {
        "PPG": "0.54252",
        "ABP": "60.43",
        "ECG": "0.79567"
    },
    {
        "PPG": "0.5347",
        "ABP": "61.213",
        "ECG": "0.77554"
    },
    {
        "PPG": "0.52786",
        "ABP": "62.973",
        "ECG": "0.77554"
    },
    {
        "PPG": "0.52199",
        "ABP": "65.906",
        "ECG": "0.73529"
    },
    {
        "PPG": "0.51515",
        "ABP": "70.795",
        "ECG": "0.71053"
    },
    {
        "PPG": "0.50929",
        "ABP": "77.445",
        "ECG": "0.66563"
    },
    {
        "PPG": "0.50342",
        "ABP": "85.267",
        "ECG": "0.64087"
    },
    {
        "PPG": "0.49756",
        "ABP": "93.286",
        "ECG": "0.60526"
    },
    {
        "PPG": "0.49169",
        "ABP": "100.72",
        "ECG": "0.58514"
    },
    {
        "PPG": "0.48583",
        "ABP": "106.19",
        "ECG": "0.56966"
    },
    {
        "PPG": "0.47898",
        "ABP": "109.91",
        "ECG": "0.54954"
    },
    {
        "PPG": "0.47312",
        "ABP": "111.86",
        "ECG": "0.55573"
    },
    {
        "PPG": "0.46628",
        "ABP": "111.86",
        "ECG": "0.5356"
    },
    {
        "PPG": "0.46041",
        "ABP": "110.69",
        "ECG": "0.54025"
    },
    {
        "PPG": "0.45455",
        "ABP": "108.34",
        "ECG": "0.52477"
    },
    {
        "PPG": "0.44966",
        "ABP": "105.02",
        "ECG": "0.55573"
    },
    {
        "PPG": "0.44477",
        "ABP": "100.91",
        "ECG": "0.54954"
    },
    {
        "PPG": "0.43891",
        "ABP": "96.024",
        "ECG": "0.57585"
    },
    {
        "PPG": "0.43304",
        "ABP": "91.134",
        "ECG": "0.55573"
    },
    {
        "PPG": "0.42717",
        "ABP": "86.05",
        "ECG": "0.56502"
    },
    {
        "PPG": "0.42131",
        "ABP": "81.552",
        "ECG": "0.52012"
    },
    {
        "PPG": "0.41544",
        "ABP": "77.445",
        "ECG": "0.51548"
    },
    {
        "PPG": "0.41153",
        "ABP": "74.316",
        "ECG": "0.50464"
    },
    {
        "PPG": "0.40665",
        "ABP": "72.164",
        "ECG": "0.5"
    },
    {
        "PPG": "0.40176",
        "ABP": "70.991",
        "ECG": "0.47523"
    },
    {
        "PPG": "0.39589",
        "ABP": "70.6",
        "ECG": "0.48452"
    },
    {
        "PPG": "0.39003",
        "ABP": "70.991",
        "ECG": "0.4644"
    },
    {
        "PPG": "0.38514",
        "ABP": "71.578",
        "ECG": "0.47523"
    }
]